Workbook

Sheet Sheet1
A1: Region | B1: Property_Type | C1: Average_Price | D1: Sales_Volume | E1: Year | F1: Mortgage_Rate | G1: Deposit_Percent | H1: Energy_Rating | I1: New_Build | J1: Buyer_Type
A2: London | B2: Detached | C2: 785000 | D2: 1200 | E2: 2023 | F2: 6.1 | G2: 18 | H2: B | I2: Yes | J2: Investor
A3: South East | B3: Flat | C3: 298000 | D3: 1200 | E3: 2024 | F3: 5.4 | G3: 12 | H3: C | I3: No | J3: First Timer
A4: North West | B4: Terraced | C4: 252000 | D4: 1990 | E4: 2023 | F4: 6.3 | G4: 10 | H4: D | I4: No | J4: First Timer
A5: Yorkshire | B5: Semi Detached | C5: 305000 | D5: 1840 | E5: 2024 | F5: 5.2 | G5: 15 | H5: C | I5: No | J5: Upsizer
A6: East Midlands | B6: Flat | C6: 218000 | D6: 740 | E6: 2023 | F6: 6.5 | G6: 8 | H6: D | I6: No | J6: First Timer
A7: West Midlands | B7: Detached | C7: 435000 | D7: 1320 | E7: 2024 | F7: 5.1 | G7: 10 | H7: B | I7: Yes | J7: Investor
A8: South West | B8: Terraced | C8: 318000 | D8: 1760 | E8: 2023 | F8: 6.4 | G8: 21 | H8: C | I8: No | J8: First Timer
A9: North East | B9: Flat | C9: 168000 | D9: 1880 | E9: 2024 | F9: 5.3 | G9: 5 | H9: D | I9: No | J9: First Timer
A10: East of England | B10: Detached | C10: 512000 | D10: 1490 | E10: 2023 | F10: 6.2 | G10: 22 | H10: B | I10: Yes | J10: Upsizer
A11: London | B11: Flat | C11: 438000 | D11: 2600 | E11: 2024 | F11: 5 | G11: 12 | H11: C | I11: No | J11: First Timer
A12: South East | B12: Semi Detached | C12: 428000 | D12: 2050 | E12: 2024 | F12: 5.3 | G12: 15 | H12: B | I12: No | J12: Upsizer
A13: North West | B13: Detached | C13: 392000 | D13: 1410 | E13: 2023 | F13: 6.4 | G13: 18 | H13: C | I13: Yes | J13: Investor
A14: Yorkshire | B14: Terraced | C14: 240000 | D14: 2140 | E14: 2024 | F14: 5.5 | G14: 10 | H14: D | I14: No | J14: First Timer
A15: East Midlands | B15: Semi Detached | C15: 322000 | D15: 1580 | E15: 2024 | F15: 5.4 | G15: 14 | H15: C | I15: No | J15: Upsizer
A16: West Midlands | B16: Flat | C16: 228000 | D16: 2100 | E16: 2023 | F16: 6.6 | G16: 7 | H16: D | I16: No | J16: First Timer
A17: South West | B17: Detached | C17: 480000 | D17: 1300 | E17: 2024 | F17: 5.2 | G17: 20 | H17: B | I17: Yes | J17: Investor
A18: North East | B18: Terraced | C18: 212000 | D18: 1820 | E18: 2023 | F18: 6.7 | G18: 6 | H18: D | I18: No | J18: First Timer
A19: East of England | B19: Flat | C19: 273000 | D19: 2430 | E19: 2024 | F19: 5.1 | G19: 10 | H19: C | I19: No | J19: First Timer
... A97: West Midlands | B97: Detached | C97: 445000 | D97: 1400 | E97: 2023 | F97: 6.1 | G97: 20 | H97: B | I97: Yes | J97: Investor
A98: South West | B98: Terraced | C98: 330000 | D98: 2050 | E98: 2024 | F98: 5.3 | G98: 10 | H98: C | I98: No | J98: First Timer
A99: North East | B99: Flat | C99: 175000 | D99: 2200 | E99: 2023 | F99: 6.4 | G99: 5 | H99: D | I99: No | J99: First Timer
A100: East of England | B100: Detached | C100: 525000 | D100: 1530 | E100: 2024 | F100: 5.1 | G100: 22 | H100: B | I100: Yes | J100: Upsizer
A101: London | B101: Flat | C101: 450000 | D101: 2680 | E101: 2024 | F101: 5 | G101: 12 | H101: C | I101: No | J101: First Timer
A102: South East | B102: Semi Detached | C102: 432000 | D102: 2120 | E102: 2023 | F102: 6.1 | G102: 15 | H102: B | I102: No | J102: Upsizer
A103: North West | B103: Detached | C103: 398000 | D103: 1460 | E103: 2024 | F103: 5.3 | G103: 18 | H103: C | I103: Yes | J103: Investor
A104: Yorkshire | B104: Terraced | C104: 248000 | D104: 2200 | E104: 2023 | F104: 6.5 | G104: 10 | H104: D | I104: No | J104: First Timer
A105: East Midlands | B105: Semi Detached | C105: 330000 | D105: 1620 | E105: 2024 | F105: 5.4 | G105: 14 | H105: C | I105: No | J105: Upsizer
A106: West Midlands | B106: Flat | C106: 232000 | D106: 2230 | E106: 2024 | F106: 5.3 | G106: 7 | H106: D | I106: No | J106: First Timer
A107: South West | B107: Detached | C107: 495000 | D107: 1450 | E107: 2023 | F107: 6.2 | G107: 20 | H107: B | I107: Yes | J107: Investor
A108: North East | B108: Terraced | C108: 218000 | D108: 1880 | E108: 2024 | F108: 5.3 | G108: 6 | H108: D | I108: No | J108: First Timer
A109: East of England | B109: Flat | C109: 282000 | D109: 2510 | E109: 2024 | F109: 5.2 | G109: 10 | H109: C | I109: No | J109: First Timer
A110: London | B110: Terraced | C110: 560000 | D110: 2300 | E110: 2024 | F110: 5.1 | G110: 15 | H110: B | I110: No | J110: Upsizer
... A187: West Midlands | B187: Detached | C187: 460000 | D187: 1420 | E187: 2023 | F187: 6.1 | G187: 20 | H187: B | I187: Yes | J187: Investor
A188: South West | B188: Terraced | C188: 345000 | D188: 2120 | E188: 2024 | F188: 5.3 | G188: 10 | H188: C | I188: No | J188: First Timer
A189: North East | B189: Flat | C189: 185000 | D189: 2200 | E189: 2023 | F189: 6.4 | G189: 5 | H189: D | I189: No | J189: First Timer
A190: East of England | B190: Detached | C190: 545000 | D190: 1620 | E190: 2024 | F190: 5.2 | G190: 22 | H190: B | I190: Yes | J190: Upsizer
A191: London | B191: Flat | C191: 460000 | D191: 2750 | E191: 2024 | F191: 5 | G191: 12 | H191: C | I191: No | J191: First Timer
A192: South East | B192: Semi Detached | C192: 450000 | D192: 2200 | E192: 2024 | F192: 5.3 | G192: 15 | H192: B | I192: No | J192: Upsizer
A193: North West | B193: Detached | C193: 405000 | D193: 1500 | E193: 2023 | F193: 6.3 | G193: 18 | H193: C | I193: Yes | J193: Investor
A194: Yorkshire | B194: Terraced | C194: 255000 | D194: 2300 | E194: 2024 | F194: 5.5 | G194: 10 | H194: D | I194: No | J194: First Timer
A195: East Midlands | B195: Semi Detached | C195: 340000 | D195: 1700 | E195: 2023 | F195: 6.1 | G195: 14 | H195: C | I195: No | J195: Upsizer
A196: West Midlands | B196: Flat | C196: 245000 | D196: 2300 | E196: 2024 | F196: 5.3 | G196: 7 | H196: D | I196: No | J196: First Timer
A197: South West | B197: Detached | C197: 510000 | D197: 1520 | E197: 2024 | F197: 5.1 | G197: 20 | H197: B | I197: Yes | J197: Investor
A198: North East | B198: Terraced | C198: 230000 | D198: 1950 | E198: 2023 | F198: 6.5 | G198: 6 | H198: D | I198: No | J198: First Timer
A199: East of England | B199: Flat | C199: 295000 | D199: 2580 | E199: 2024 | F199: 5.2 | G199: 10 | H199: C | I199: No | J199: First Timer
A200: London | B200: Terraced | C200: 575000 | D200: 2400 | E200: 2023 | F200: 6 | G200: 15 | H200: B | I200: No | J200: Upsizer
... A277: West Midlands | B277: Detached | C277: 490000 | D277: 1550 | E277: 2024 | F277: 5.2 | G277: 20 | H277: B | I277: Yes | J277: Investor
A278: South West | B278: Terraced | C278: 360000 | D278: 2250 | E278: 2024 | F278: 5.3 | G278: 10 | H278: C | I278: No | J278: First Timer
A279: North East | B279: Flat | C279: 200000 | D279: 2350 | E279: 2023 | F279: 6.4 | G279: 5 | H279: D | I279: No | J279: First Timer
A280: East of England | B280: Detached | C280: 570000 | D280: 1750 | E280: 2024 | F280: 5.1 | G280: 22 | H280: B | I280: Yes | J280: Upsizer
A281: London | B281: Flat | C281: 490000 | D281: 2900 | E281: 2024 | F281: 5 | G281: 12 | H281: C | I281: No | J281: First Timer
A282: South East | B282: Semi Detached | C282: 470000 | D282: 2350 | E282: 2023 | F282: 6 | G282: 15 | H282: B | I282: No | J282: Upsizer
A283: North West | B283: Detached | C283: 420000 | D283: 1600 | E283: 2024 | F283: 5.3 | G283: 18 | H283: C | I283: Yes | J283: Investor
A284: Yorkshire | B284: Terraced | C284: 270000 | D284: 2450 | E284: 2023 | F284: 6.5 | G284: 10 | H284: D | I284: No | J284: First Timer
A285: East Midlands | B285: Semi Detached | C285: 360000 | D285: 1850 | E285: 2024 | F285: 5.4 | G285: 14 | H285: C | I285: No | J285: Upsizer
A286: West Midlands | B286: Flat | C286: 260000 | D286: 2450 | E286: 2024 | F286: 5.3 | G286: 7 | H286: D | I286: No | J286: First Timer
A287: South West | B287: Detached | C287: 530000 | D287: 1650 | E287: 2023 | F287: 6 | G287: 20 | H287: B | I287: Yes | J287: Investor
A288: North East | B288: Terraced | C288: 250000 | D288: 2100 | E288: 2024 | F288: 5.3 | G288: 6 | H288: D | I288: No | J288: First Timer
A289: East of England | B289: Flat | C289: 315000 | D289: 2700 | E289: 2024 | F289: 5.2 | G289: 10 | H289: C | I289: No | J289: First Timer
A290: London | B290: Terraced | C290: 600000 | D290: 2550 | E290: 2023 | F290: 6.1 | G290: 15 | H290: B | I290: No | J290: Upsizer
... A353: West Midlands | B353: Detached | C353: 435000 | D353: 1320 | E353: 2024 | F353: 5.1 | G353: 20 | H353: B | I353: Yes | J353: Investor
A354: South West | B354: Terraced | C354: 318000 | D354: 1760 | E354: 2023 | F354: 6.4 | G354: 10 | H354: C | I354: No | J354: First Timer
A355: Yorkshire | B355: Semi Detached | C355: 325000 | D355: 1980 | E355: 2023 | F355: 6.2 | G355: 15 | H355: C | I355: No | J355: Upsizer
A356: East Midlands | B356: Flat | C356: 230000 | D356: 2250 | E356: 2023 | F356: 6.5 | G356: 8 | H356: D | I356: No | J356: First Timer
A357: West Midlands | B357: Detached | C357: 455000 | D357: 1400 | E357: 2024 | F357: 5.1 | G357: 20 | H357: B | I357: Yes | J357: Investor
A358: South West | B358: Terraced | C358: 340000 | D358: 2050 | E358: 2024 | F358: 5.3 | G358: 10 | H358: C | I358: No | J358: First Timer
A359: North East | B359: Flat | C359: 180000 | D359: 2200 | E359: 2023 | F359: 6.4 | G359: 5 | H359: D | I359: No | J359: First Timer
A360: East of England | B360: Detached | C360: 540000 | D360: 1530 | E360: 2024 | F360: 5.1 | G360: 22 | H360: B | I360: Yes | J360: Upsizer
A361: London | B361: Flat | C361: 470000 | D361: 2680 | E361: 2024 | F361: 5 | G361: 12 | H361: C | I361: No | J361: First Timer
A362: South East | B362: Semi Detached | C362: 440000 | D362: 2120 | E362: 2023 | F362: 6.1 | G362: 15 | H362: B | I362: No | J362: Upsizer
A363: North West | B363: Detached | C363: 405000 | D363: 1460 | E363: 2024 | F363: 5.3 | G363: 18 | H363: C | I363: Yes | J363: Investor
A364: Yorkshire | B364: Terraced | C364: 255000 | D364: 2200 | E364: 2023 | F364: 6.5 | G364: 10 | H364: D | I364: No | J364: First Timer
A365: East Midlands | B365: Semi Detached | C365: 345000 | D365: 1620 | E365: 2024 | F365: 5.4 | G365: 14 | H365: C | I365: No | J365: Upsizer
A366: West Midlands | B366: Flat | C366: 240000 | D366: 2230 | E366: 2024 | F366: 5.3 | G366: 7 | H366: D | I366: No | J366: First Timer
A367: South West | B367: Detached | C367: 510000 | D367: 1450 | E367: 2023 | F367: 6.2 | G367: 20 | H367: B | I367: Yes | J367: Investor
A368: North East | B368: Terraced | C368: 225000 | D368: 1880 | E368: 2024 | F368: 5.3 | G368: 6 | H368: D | I368: No | J368: First Timer
A369: East of England | B369: Flat | C369: 290000 | D369: 2510 | E369: 2024 | F369: 5.2 | G369: 10 | H369: C | I369: No | J369: First Timer
A370: London | B370: Terraced | C370: 580000 | D370: 2300 | E370: 2024 | F370: 5.1 | G370: 15 | H370: B | I370: No | J370: Upsizer
... A442: East Midlands | B442: Flat | C442: 400000 | D442: 2250 | E442: 2024 | F442: 5.4 | G442: 8 | H442: D | I442: No | J442: First Timer
A443: West Midlands | B443: Detached | C443: 470000 | D443: 1400 | E443: 2024 | F443: 5.1 | G443: 20 | H443: B | I443: Yes | J443: Investor
A444: South West | B444: Terraced | C444: 300000 | D444: 500 | E444: 2024 | F444: 5.3 | G444: 10 | H444: C | I444: No | J444: First Timer
A445: North East | B445: Flat | C445: 394000 | D445: 2200 | E445: 2023 | F445: 6.4 | G445: 5 | H445: D | I445: No | J445: First Timer
A446: East of England | B446: Detached | C446: 700000 | D446: 740 | E446: 2024 | F446: 5.1 | G446: 22 | H446: B | I446: Yes | J446: Upsizer
A447: London | B447: Flat | C447: 490000 | D447: 2680 | E447: 2024 | F447: 5 | G447: 12 | H447: C | I447: No | J447: First Timer
A448: South East | B448: Semi Detached | C448: 440000 | D448: 740 | E448: 2023 | F448: 6.1 | G448: 15 | H448: B | I448: No | J448: Upsizer
A449: North West | B449: Detached | C449: 410000 | D449: 1460 | E449: 2024 | F449: 5.3 | G449: 18 | H449: C | I449: Yes | J449: Investor
A450: Yorkshire | B450: Terraced | C450: 260000 | D450: 740 | E450: 2023 | F450: 6.5 | G450: 10 | H450: D | I450: No | J450: First Timer
A451: East Midlands | B451: Semi Detached | C451: 355000 | D451: 1620 | E451: 2024 | F451: 5.4 | G451: 14 | H451: C | I451: No | J451: Upsizer
A452: West Midlands | B452: Flat | C452: 250000 | D452: 2230 | E452: 2024 | F452: 5.3 | G452: 7 | H452: D | I452: No | J452: First Timer
A453: South West | B453: Detached | C453: 290000 | D453: 1450 | E453: 2024 | F453: 5.1 | G453: 20 | H453: B | I453: Yes | J453: Investor
A454: North East | B454: Terraced | C454: 230000 | D454: 740 | E454: 2024 | F454: 5.3 | G454: 6 | H454: D | I454: No | J454: First Timer
A455: East of England | B455: Flat | C455: 310000 | D455: 2510 | E455: 2024 | F455: 5.3 | G455: 10 | H455: C | I455: No | J455: First Timer
A456: London | B456: Terraced | C456: 600000 | D456: 740 | E456: 2024 | F456: 5.1 | G456: 15 | H456: B | I456: No | J456: Upsizer
A457: South East | B457: Detached | C457: 620000 | D457: 740 | E457: 2024 | F457: 5.3 | G457: 22 | H457: A | I457: Yes | J457: Investor
A458: North West | B458: Flat | C458: 230000 | D458: 740 | E458: 2023 | F458: 6.4 | G458: 5 | H458: D | I458: No | J458: First Timer
A459: Yorkshire | B459: Detached | C459: 415000 | D459: 1400 | E459: 2024 | F459: 5.1 | G459: 20 | H459: B | I459: Yes | J459: Upsizer
A460: East Midlands | B460: Terraced | C460: 305000 | D460: 740 | E460: 2023 | F460: 6.5 | G460: 10 | H460: C | I460: No | J460: First Timer
A461: West Midlands | B461: Semi Detached | C461: 360000 | D461: 740 | E461: 2024 | F461: 5.3 | G461: 18 | H461: B | I461: No | J461: Upsizer
A462: South West | B462: Flat | C462: 300000 | D462: 740 | E462: 2024 | F462: 5.2 | G462: 12 | H462: C | I462: No | J462: First Timer
...

Sheet Copy
A1: Region | B1: Property_Type | C1: Average_Price | D1: Sales_Volume | E1: Year | F1: Mortgage_Rate | G1: Deposit_Percent | H1: Energy_Rating | I1: New_Build | J1: Buyer_Type | K1: Affordability_Index | L1: Monthly_Mortgage_cost | M1: Total Interest Paid | N1: 25-Year total cost | O1: Loan Amount | P1: Investment_Score | S1: Investment_Score_1
A2: North East | B2: Flat | C2: 175000 | D2: 2200 | E2: 2023 | F2: 6.4 | G2: 5 | H2: D | I2: No | J2: First Timer | K2: =C2/D2 -> 79.545455 | L2: =PMT(F2/100/12, 300, -(C2 * (1 - G2/100))) -> 1112.1657 | M2: =-CUMIPMT(F2/1200,300,O2,1,300,0) -> 167399.72 | N2: =O2+M2 -> 333649.72 | O2: =C2*(1-G2/100) -> 166250 | P2: 880.30377 | R2: =IF(H2="A","4",IF(H2="B","3",IF(H2="C","2",IF(H2="D","1",0)))) -> 1 | S2: =D2*0.4 +R2*0.3 +(1/(K2*0.3)) -> 880.3419
A3: Yorkshire | B3: Flat | C3: 190000 | D3: 2380 | E3: 2024 | F3: 5.5 | G3: 5 | H3: D | I3: No | J3: First Timer | K3: =C3/D3 -> 79.831933 | L3: =PMT(F3/100/12, 300, -(C3 * (1 - G3/100))) -> 1108.4279 | M3: =-CUMIPMT(F3/1200,300,O3,1,300,0) -> 152028.38 | N3: =O3+M3 -> 332528.38 | O3: =C3*(1-G3/100) -> 180500 | P3: 952.30376 | R3: =IF(H3="A","4",IF(H3="B","3",IF(H3="C","2",IF(H3="D","1",0)))) -> 1 | S3: =D3*0.4 +R3*0.3 +(1/(K3*0.3)) -> 952.34175
A4: North East | B4: Flat | C4: 225000 | D4: 2800 | E4: 2024 | F4: 5.4 | G4: 8 | H4: D | I4: No | J4: First Timer | K4: =C4/D4 -> 80.357143 | L4: =PMT(F4/100/12, 300, -(C4 * (1 - G4/100))) -> 1258.8289 | M4: =-CUMIPMT(F4/1200,300,O4,1,300,0) -> 170648.68 | N4: =O4+M4 -> 377648.68 | O4: =C4*(1-G4/100) -> 207000 | P4: 1120.3037 | R4: =IF(H4="A","4",IF(H4="B","3",IF(H4="C","2",IF(H4="D","1",0)))) -> 1 | S4: =D4*0.4 +R4*0.3 +(1/(K4*0.3)) -> 1120.3415
A5: North East | B5: Flat | C5: 230000 | D5: 2850 | E5: 2024 | F5: 5.4 | G5: 8 | H5: D | I5: No | J5: First Timer | K5: =C5/D5 -> 80.701754 | L5: =PMT(F5/100/12, 300, -(C5 * (1 - G5/100))) -> 1286.8029 | M5: =-CUMIPMT(F5/1200,300,O5,1,300,0) -> 174440.87 | N5: =O5+M5 -> 386040.87 | O5: =C5*(1-G5/100) -> 211600 | P5: 1140.3037 | R5: =IF(H5="A","4",IF(H5="B","3",IF(H5="C","2",IF(H5="D","1",0)))) -> 1 | S5: =D5*0.4 +R5*0.3 +(1/(K5*0.3)) -> 1140.3413
A6: Yorkshire | B6: Flat | C6: 194000 | D6: 2400 | E6: 2024 | F6: 5.4 | G6: 5 | H6: D | I6: No | J6: First Timer | K6: =C6/D6 -> 80.833333 | L6: =PMT(F6/100/12, 300, -(C6 * (1 - G6/100))) -> 1120.7834 | M6: =-CUMIPMT(F6/1200,300,O6,1,300,0) -> 151935.03 | N6: =O6+M6 -> 336235.03 | O6: =C6*(1-G6/100) -> 184300 | P6: 960.30371 | R6: =IF(H6="A","4",IF(H6="B","3",IF(H6="C","2",IF(H6="D","1",0)))) -> 1 | S6: =D6*0.4 +R6*0.3 +(1/(K6*0.3)) -> 960.34124
A7: North East | B7: Flat | C7: 235000 | D7: 2900 | E7: 2024 | F7: 5.4 | G7: 8 | H7: D | I7: No | J7: First Timer | K7: =C7/D7 -> 81.034483 | L7: =PMT(F7/100/12, 300, -(C7 * (1 - G7/100))) -> 1314.7769 | M7: =-CUMIPMT(F7/1200,300,O7,1,300,0) -> 178233.06 | N7: =O7+M7 -> 394433.06 | O7: =C7*(1-G7/100) -> 216200 | P7: 1160.3037 | R7: =IF(H7="A","4",IF(H7="B","3",IF(H7="C","2",IF(H7="D","1",0)))) -> 1 | S7: =D7*0.4 +R7*0.3 +(1/(K7*0.3)) -> 1160.3411
A8: North East | B8: Flat | C8: 236000 | D8: 2910 | E8: 2024 | F8: 5.4 | G8: 8 | H8: D | I8: No | J8: First Timer | K8: =C8/D8 -> 81.099656 | L8: =PMT(F8/100/12, 300, -(C8 * (1 - G8/100))) -> 1320.3717 | M8: =-CUMIPMT(F8/1200,300,O8,1,300,0) -> 178991.5 | N8: =O8+M8 -> 396111.5 | O8: =C8*(1-G8/100) -> 217120 | P8: 1164.3037 | R8: =IF(H8="A","4",IF(H8="B","3",IF(H8="C","2",IF(H8="D","1",0)))) -> 1 | S8: =D8*0.4 +R8*0.3 +(1/(K8*0.3)) -> 1164.3411
A9: North East | B9: Flat | C9: 220000 | D9: 2700 | E9: 2024 | F9: 5.4 | G9: 8 | H9: D | I9: No | J9: First Timer | K9: =C9/D9 -> 81.481481 | L9: =PMT(F9/100/12, 300, -(C9 * (1 - G9/100))) -> 1230.855 | M9: =-CUMIPMT(F9/1200,300,O9,1,300,0) -> 166856.49 | N9: =O9+M9 -> 369256.49 | O9: =C9*(1-G9/100) -> 202400 | P9: 1080.3037 | R9: =IF(H9="A","4",IF(H9="B","3",IF(H9="C","2",IF(H9="D","1",0)))) -> 1 | S9: =D9*0.4 +R9*0.3 +(1/(K9*0.3)) -> 1080.3409
A10: Yorkshire | B10: Flat | C10: 200000 | D10: 2450 | E10: 2024 | F10: 5.4 | G10: 5 | H10: D | I10: No | J10: First Timer | K10: =C10/D10 -> 81.632653 | L10: =PMT(F10/100/12, 300, -(C10 * (1 - G10/100))) -> 1155.4468 | M10: =-CUMIPMT(F10/1200,300,O10,1,300,0) -> 156634.05 | N10: =O10+M10 -> 346634.05 | O10: =C10*(1-G10/100) -> 190000 | P10: 980.30367 | R10: =IF(H10="A","4",IF(H10="B","3",IF(H10="C","2",IF(H10="D","1",0)))) -> 1 | S10: =D10*0.4 +R10*0.3 +(1/(K10*0.3)) -> 980.34083
A11: Yorkshire | B11: Flat | C11: 198000 | D11: 2420 | E11: 2023 | F11: 6.6 | G11: 5 | H11: D | I11: No | J11: First Timer | K11: =C11/D11 -> 81.818182 | L11: =PMT(F11/100/12, 300, -(C11 * (1 - G11/100))) -> 1281.8434 | M11: =-CUMIPMT(F11/1200,300,O11,1,300,0) -> 196453.01 | N11: =O11+M11 -> 384553.01 | O11: =C11*(1-G11/100) -> 188100 | P11: 968.30367 | R11: =IF(H11="A","4",IF(H11="B","3",IF(H11="C","2",IF(H11="D","1",0)))) -> 1 | S11: =D11*0.4 +R11*0.3 +(1/(K11*0.3)) -> 968.34074
A12: North East | B12: Flat | C12: 180000 | D12: 2200 | E12: 2023 | F12: 6.4 | G12: 5 | H12: D | I12: No | J12: First Timer | K12: =C12/D12 -> 81.818182 | L12: =PMT(F12/100/12, 300, -(C12 * (1 - G12/100))) -> 1143.9419 | M12: =-CUMIPMT(F12/1200,300,O12,1,300,0) -> 172182.57 | N12: =O12+M12 -> 343182.57 | O12: =C12*(1-G12/100) -> 171000 | P12: 880.30367 | R12: =IF(H12="A","4",IF(H12="B","3",IF(H12="C","2",IF(H12="D","1",0)))) -> 1 | S12: =D12*0.4 +R12*0.3 +(1/(K12*0.3)) -> 880.34074
A13: Yorkshire | B13: Flat | C13: 188000 | D13: 2290 | E13: 2023 | F13: 6.5 | G13: 5 | H13: D | I13: No | J13: First Timer | K13: =C13/D13 -> 82.09607 | L13: =PMT(F13/100/12, 300, -(C13 * (1 - G13/100))) -> 1205.92 | M13: =-CUMIPMT(F13/1200,300,O13,1,300,0) -> 183176 | N13: =O13+M13 -> 361776 | O13: =C13*(1-G13/100) -> 178600 | P13: 916.30365 | R13: =IF(H13="A","4",IF(H13="B","3",IF(H13="C","2",IF(H13="D","1",0)))) -> 1 | S13: =D13*0.4 +R13*0.3 +(1/(K13*0.3)) -> 916.3406
... A25: North East | B25: Flat | C25: 188000 | D25: 2250 | E25: 2024 | F25: 5.4 | G25: 8 | H25: D | I25: No | J25: First Timer | K25: =C25/D25 -> 83.555556 | L25: =PMT(F25/100/12, 300, -(C25 * (1 - G25/100))) -> 1051.8215 | M25: =-CUMIPMT(F25/1200,300,O25,1,300,0) -> 142586.45 | N25: =O25+M25 -> 315546.45 | O25: =C25*(1-G25/100) -> 172960 | P25: 900.30359 | R25: =IF(H25="A","4",IF(H25="B","3",IF(H25="C","2",IF(H25="D","1",0)))) -> 1 | S25: =D25*0.4 +R25*0.3 +(1/(K25*0.3)) -> 900.33989
A26: North East | B26: Flat | C26: 180000 | D26: 2150 | E26: 2024 | F26: 5.4 | G26: 8 | H26: D | I26: No | J26: First Timer | K26: =C26/D26 -> 83.72093 | L26: =PMT(F26/100/12, 300, -(C26 * (1 - G26/100))) -> 1007.0631 | M26: =-CUMIPMT(F26/1200,300,O26,1,300,0) -> 136518.94 | N26: =O26+M26 -> 302118.94 | O26: =C26*(1-G26/100) -> 165600 | P26: 860.30358 | R26: =IF(H26="A","4",IF(H26="B","3",IF(H26="C","2",IF(H26="D","1",0)))) -> 1 | S26: =D26*0.4 +R26*0.3 +(1/(K26*0.3)) -> 860.33981
A27: North East | B27: Flat | C27: 166000 | D27: 1980 | E27: 2023 | F27: 6.4 | G27: 8 | H27: D | I27: No | J27: First Timer | K27: =C27/D27 -> 83.838384 | L27: =PMT(F27/100/12, 300, -(C27 * (1 - G27/100))) -> 1021.6539 | M27: =-CUMIPMT(F27/1200,300,O27,1,300,0) -> 153776.16 | N27: =O27+M27 -> 306496.16 | O27: =C27*(1-G27/100) -> 152720 | P27: 792.30358 | R27: =IF(H27="A","4",IF(H27="B","3",IF(H27="C","2",IF(H27="D","1",0)))) -> 1 | S27: =D27*0.4 +R27*0.3 +(1/(K27*0.3)) -> 792.33976
A28: Yorkshire | B28: Flat | C28: 210000 | D28: 2500 | E28: 2024 | F28: 5.4 | G28: 5 | H28: D | I28: No | J28: First Timer | K28: =C28/D28 -> 84 | L28: =PMT(F28/100/12, 300, -(C28 * (1 - G28/100))) -> 1213.2192 | M28: =-CUMIPMT(F28/1200,300,O28,1,300,0) -> 164465.76 | N28: =O28+M28 -> 363965.76 | O28: =C28*(1-G28/100) -> 199500 | P28: 1000.3036 | R28: =IF(H28="A","4",IF(H28="B","3",IF(H28="C","2",IF(H28="D","1",0)))) -> 1 | S28: =D28*0.4 +R28*0.3 +(1/(K28*0.3)) -> 1000.3397
A29: North East | B29: Flat | C29: 210000 | D29: 2500 | E29: 2024 | F29: 5.4 | G29: 8 | H29: D | I29: No | J29: First Timer | K29: =C29/D29 -> 84 | L29: =PMT(F29/100/12, 300, -(C29 * (1 - G29/100))) -> 1174.907 | M29: =-CUMIPMT(F29/1200,300,O29,1,300,0) -> 159272.1 | N29: =O29+M29 -> 352472.1 | O29: =C29*(1-G29/100) -> 193200 | P29: 1000.3036 | R29: =IF(H29="A","4",IF(H29="B","3",IF(H29="C","2",IF(H29="D","1",0)))) -> 1 | S29: =D29*0.4 +R29*0.3 +(1/(K29*0.3)) -> 1000.3397
A30: North East | B30: Flat | C30: 185000 | D30: 2200 | E30: 2023 | F30: 6.4 | G30: 5 | H30: D | I30: No | J30: First Timer | K30: =C30/D30 -> 84.090909 | L30: =PMT(F30/100/12, 300, -(C30 * (1 - G30/100))) -> 1175.7181 | M30: =-CUMIPMT(F30/1200,300,O30,1,300,0) -> 176965.42 | N30: =O30+M30 -> 352715.42 | O30: =C30*(1-G30/100) -> 175750 | P30: 880.30357 | R30: =IF(H30="A","4",IF(H30="B","3",IF(H30="C","2",IF(H30="D","1",0)))) -> 1 | S30: =D30*0.4 +R30*0.3 +(1/(K30*0.3)) -> 880.33964
A31: North East | B31: Flat | C31: 185000 | D31: 2200 | E31: 2024 | F31: 5.4 | G31: 8 | H31: D | I31: No | J31: First Timer | K31: =C31/D31 -> 84.090909 | L31: =PMT(F31/100/12, 300, -(C31 * (1 - G31/100))) -> 1035.0371 | M31: =-CUMIPMT(F31/1200,300,O31,1,300,0) -> 140311.14 | N31: =O31+M31 -> 310511.14 | O31: =C31*(1-G31/100) -> 170200 | P31: 880.30357 | R31: =IF(H31="A","4",IF(H31="B","3",IF(H31="C","2",IF(H31="D","1",0)))) -> 1 | S31: =D31*0.4 +R31*0.3 +(1/(K31*0.3)) -> 880.33964
A32: North East | B32: Flat | C32: 190000 | D32: 2250 | E32: 2024 | F32: 5.4 | G32: 8 | H32: D | I32: No | J32: First Timer | K32: =C32/D32 -> 84.444444 | L32: =PMT(F32/100/12, 300, -(C32 * (1 - G32/100))) -> 1063.0111 | M32: =-CUMIPMT(F32/1200,300,O32,1,300,0) -> 144103.33 | N32: =O32+M32 -> 318903.33 | O32: =C32*(1-G32/100) -> 174800 | P32: 900.30355 | R32: =IF(H32="A","4",IF(H32="B","3",IF(H32="C","2",IF(H32="D","1",0)))) -> 1 | S32: =D32*0.4 +R32*0.3 +(1/(K32*0.3)) -> 900.33947
A33: North West | B33: Flat | C33: 210000 | D33: 2480 | E33: 2024 | F33: 5.4 | G33: 5 | H33: D | I33: No | J33: First Timer | K33: =C33/D33 -> 84.677419 | L33: =PMT(F33/100/12, 300, -(C33 * (1 - G33/100))) -> 1213.2192 | M33: =-CUMIPMT(F33/1200,300,O33,1,300,0) -> 164465.76 | N33: =O33+M33 -> 363965.76 | O33: =C33*(1-G33/100) -> 199500 | P33: 992.30354 | R33: =IF(H33="A","4",IF(H33="B","3",IF(H33="C","2",IF(H33="D","1",0)))) -> 1 | S33: =D33*0.4 +R33*0.3 +(1/(K33*0.3)) -> 992.33937
A34: Yorkshire | B34: Flat | C34: 205000 | D34: 2420 | E34: 2023 | F34: 6.6 | G34: 5 | H34: D | I34: No | J34: First Timer | K34: =C34/D34 -> 84.710744 | L34: =PMT(F34/100/12, 300, -(C34 * (1 - G34/100))) -> 1327.1611 | M34: =-CUMIPMT(F34/1200,300,O34,1,300,0) -> 203398.32 | N34: =O34+M34 -> 398148.32 | O34: =C34*(1-G34/100) -> 194750 | P34: 968.30354 | R34: =IF(H34="A","4",IF(H34="B","3",IF(H34="C","2",IF(H34="D","1",0)))) -> 1 | S34: =D34*0.4 +R34*0.3 +(1/(K34*0.3)) -> 968.33935
A35: North East | B35: Flat | C35: 195000 | D35: 2300 | E35: 2023 | F35: 6.4 | G35: 8 | H35: D | I35: No | J35: First Timer | K35: =C35/D35 -> 84.782609 | L35: =PMT(F35/100/12, 300, -(C35 * (1 - G35/100))) -> 1200.1355 | M35: =-CUMIPMT(F35/1200,300,O35,1,300,0) -> 180640.66 | N35: =O35+M35 -> 360040.66 | O35: =C35*(1-G35/100) -> 179400 | P35: 920.30354 | R35: =IF(H35="A","4",IF(H35="B","3",IF(H35="C","2",IF(H35="D","1",0)))) -> 1 | S35: =D35*0.4 +R35*0.3 +(1/(K35*0.3)) -> 920.33932
A36: North East | B36: Flat | C36: 195000 | D36: 2300 | E36: 2024 | F36: 5.4 | G36: 8 | H36: D | I36: No | J36: First Timer | K36: =C36/D36 -> 84.782609 | L36: =PMT(F36/100/12, 300, -(C36 * (1 - G36/100))) -> 1090.9851 | M36: =-CUMIPMT(F36/1200,300,O36,1,300,0) -> 147895.52 | N36: =O36+M36 -> 327295.52 | O36: =C36*(1-G36/100) -> 179400 | P36: 920.30354 | R36: =IF(H36="A","4",IF(H36="B","3",IF(H36="C","2",IF(H36="D","1",0)))) -> 1 | S36: =D36*0.4 +R36*0.3 +(1/(K36*0.3)) -> 920.33932
A37: North West | B37: Flat | C37: 212000 | D37: 2500 | E37: 2023 | F37: 6.4 | G37: 5 | H37: D | I37: No | J37: First Timer | K37: =C37/D37 -> 84.8 | L37: =PMT(F37/100/12, 300, -(C37 * (1 - G37/100))) -> 1347.3094 | M37: =-CUMIPMT(F37/1200,300,O37,1,300,0) -> 202792.81 | N37: =O37+M37 -> 404192.81 | O37: =C37*(1-G37/100) -> 201400 | P37: 1000.3035 | R37: =IF(H37="A","4",IF(H37="B","3",IF(H37="C","2",IF(H37="D","1",0)))) -> 1 | S37: =D37*0.4 +R37*0.3 +(1/(K37*0.3)) -> 1000.3393
A38: North East | B38: Flat | C38: 200000 | D38: 2350 | E38: 2023 | F38: 6.4 | G38: 5 | H38: D | I38: No | J38: First Timer | K38: =C38/D38 -> 85.106383 | L38: =PMT(F38/100/12, 300, -(C38 * (1 - G38/100))) -> 1271.0466 | M38: =-CUMIPMT(F38/1200,300,O38,1,300,0) -> 191313.97 | N38: =O38+M38 -> 381313.97 | O38: =C38*(1-G38/100) -> 190000 | P38: 940.30352 | R38: =IF(H38="A","4",IF(H38="B","3",IF(H38="C","2",IF(H38="D","1",0)))) -> 1 | S38: =D38*0.4 +R38*0.3 +(1/(K38*0.3)) -> 940.33917
... A144: East of England | B144: Flat | C144: 279000 | D144: 2490 | E144: 2023 | F144: 6 | G144: 10 | H144: C | I144: No | J144: First Timer | K144: =C144/D144 -> 112.04819 | L144: =PMT(F144/100/12, 300, -(C144 * (1 - G144/100))) -> 1617.8408 | M144: =-CUMIPMT(F144/1200,300,O144,1,300,0) -> 234252.25 | N144: =O144+M144 -> 485352.25 | O144: =C144*(1-G144/100) -> 251100 | P144: 996.60268 | R144: =IF(H144="A","4",IF(H144="B","3",IF(H144="C","2",IF(H144="D","1",0)))) -> 2 | S144: =D144*0.4 +R144*0.3 +(1/(K144*0.3)) -> 996.62975
A145: West Midlands | B145: Flat | C145: 250000 | D145: 2230 | E145: 2024 | F145: 5.3 | G145: 7 | H145: D | I145: No | J145: First Timer | K145: =C145/D145 -> 112.10762 | L145: =PMT(F145/100/12, 300, -(C145 * (1 - G145/100))) -> 1400.1178 | M145: =-CUMIPMT(F145/1200,300,O145,1,300,0) -> 187535.33 | N145: =O145+M145 -> 420035.33 | O145: =C145*(1-G145/100) -> 232500 | P145: 892.30268 | R145: =IF(H145="A","4",IF(H145="B","3",IF(H145="C","2",IF(H145="D","1",0)))) -> 1 | S145: =D145*0.4 +R145*0.3 +(1/(K145*0.3)) -> 892.32973
A146: Yorkshire | B146: Terraced | C146: 240000 | D146: 2140 | E146: 2024 | F146: 5.5 | G146: 10 | H146: D | I146: No | J146: First Timer | K146: =C146/D146 -> 112.14953 | L146: =PMT(F146/100/12, 300, -(C146 * (1 - G146/100))) -> 1326.429 | M146: =-CUMIPMT(F146/1200,300,O146,1,300,0) -> 181928.69 | N146: =O146+M146 -> 397928.69 | O146: =C146*(1-G146/100) -> 216000 | P146: 856.30267 | R146: =IF(H146="A","4",IF(H146="B","3",IF(H146="C","2",IF(H146="D","1",0)))) -> 1 | S146: =D146*0.4 +R146*0.3 +(1/(K146*0.3)) -> 856.32972
A147: East of England | B147: Flat | C147: 276000 | D147: 2460 | E147: 2024 | F147: 5.1 | G147: 10 | H147: C | I147: No | J147: First Timer | K147: =C147/D147 -> 112.19512 | L147: =PMT(F147/100/12, 300, -(C147 * (1 - G147/100))) -> 1466.6308 | M147: =-CUMIPMT(F147/1200,300,O147,1,300,0) -> 191589.23 | N147: =O147+M147 -> 439989.23 | O147: =C147*(1-G147/100) -> 248400 | P147: 984.60267 | R147: =IF(H147="A","4",IF(H147="B","3",IF(H147="C","2",IF(H147="D","1",0)))) -> 2 | S147: =D147*0.4 +R147*0.3 +(1/(K147*0.3)) -> 984.62971
A148: North West | B148: Terraced | C148: 248000 | D148: 2210 | E148: 2024 | F148: 5.5 | G148: 8 | H148: D | I148: No | J148: First Timer | K148: =C148/D148 -> 112.21719 | L148: =PMT(F148/100/12, 300, -(C148 * (1 - G148/100))) -> 1401.102 | M148: =-CUMIPMT(F148/1200,300,O148,1,300,0) -> 192170.61 | N148: =O148+M148 -> 420330.61 | O148: =C148*(1-G148/100) -> 228160 | P148: 884.30267 | R148: =IF(H148="A","4",IF(H148="B","3",IF(H148="C","2",IF(H148="D","1",0)))) -> 1 | S148: =D148*0.4 +R148*0.3 +(1/(K148*0.3)) -> 884.3297
A149: South West | B149: Flat | C149: 255000 | D149: 2270 | E149: 2024 | F149: 5.2 | G149: 12 | H149: C | I149: No | J149: First Timer | K149: =C149/D149 -> 112.3348 | L149: =PMT(F149/100/12, 300, -(C149 * (1 - G149/100))) -> 1338.1006 | M149: =-CUMIPMT(F149/1200,300,O149,1,300,0) -> 177030.18 | N149: =O149+M149 -> 401430.18 | O149: =C149*(1-G149/100) -> 224400 | P149: 908.60267 | R149: =IF(H149="A","4",IF(H149="B","3",IF(H149="C","2",IF(H149="D","1",0)))) -> 2 | S149: =D149*0.4 +R149*0.3 +(1/(K149*0.3)) -> 908.62967
A150: East of England | B150: Flat | C150: 273000 | D150: 2430 | E150: 2024 | F150: 5.1 | G150: 10 | H150: C | I150: No | J150: First Timer | K150: =C150/D150 -> 112.34568 | L150: =PMT(F150/100/12, 300, -(C150 * (1 - G150/100))) -> 1450.6891 | M150: =-CUMIPMT(F150/1200,300,O150,1,300,0) -> 189506.74 | N150: =O150+M150 -> 435206.74 | O150: =C150*(1-G150/100) -> 245700 | P150: 972.60267 | R150: =IF(H150="A","4",IF(H150="B","3",IF(H150="C","2",IF(H150="D","1",0)))) -> 2 | S150: =D150*0.4 +R150*0.3 +(1/(K150*0.3)) -> 972.62967
A151: East of England | B151: Flat | C151: 282000 | D151: 2510 | E151: 2024 | F151: 5.2 | G151: 10 | H151: C | I151: No | J151: First Timer | K151: =C151/D151 -> 112.3506 | L151: =PMT(F151/100/12, 300, -(C151 * (1 - G151/100))) -> 1513.4133 | M151: =-CUMIPMT(F151/1200,300,O151,1,300,0) -> 200223.98 | N151: =O151+M151 -> 454023.98 | O151: =C151*(1-G151/100) -> 253800 | P151: 1004.6027 | R151: =IF(H151="A","4",IF(H151="B","3",IF(H151="C","2",IF(H151="D","1",0)))) -> 2 | S151: =D151*0.4 +R151*0.3 +(1/(K151*0.3)) -> 1004.6297
A152: East of England | B152: Flat | C152: 285000 | D152: 2530 | E152: 2023 | F152: 6 | G152: 10 | H152: C | I152: No | J152: First Timer | K152: =C152/D152 -> 112.64822 | L152: =PMT(F152/100/12, 300, -(C152 * (1 - G152/100))) -> 1652.6331 | M152: =-CUMIPMT(F152/1200,300,O152,1,300,0) -> 239289.93 | N152: =O152+M152 -> 495789.93 | O152: =C152*(1-G152/100) -> 256500 | P152: 1012.6027 | R152: =IF(H152="A","4",IF(H152="B","3",IF(H152="C","2",IF(H152="D","1",0)))) -> 2 | S152: =D152*0.4 +R152*0.3 +(1/(K152*0.3)) -> 1012.6296
A153: Yorkshire | B153: Terraced | C153: 248000 | D153: 2200 | E153: 2023 | F153: 6.5 | G153: 10 | H153: D | I153: No | J153: First Timer | K153: =C153/D153 -> 112.72727 | L153: =PMT(F153/100/12, 300, -(C153 * (1 - G153/100))) -> 1507.0624 | M153: =-CUMIPMT(F153/1200,300,O153,1,300,0) -> 228918.72 | N153: =O153+M153 -> 452118.72 | O153: =C153*(1-G153/100) -> 223200 | P153: 880.30266 | R153: =IF(H153="A","4",IF(H153="B","3",IF(H153="C","2",IF(H153="D","1",0)))) -> 1 | S153: =D153*0.4 +R153*0.3 +(1/(K153*0.3)) -> 880.32957
A154: North West | B154: Terraced | C154: 254000 | D154: 2240 | E154: 2023 | F154: 6.3 | G154: 10 | H154: D | I154: No | J154: First Timer | K154: =C154/D154 -> 113.39286 | L154: =PMT(F154/100/12, 300, -(C154 * (1 - G154/100))) -> 1515.0773 | M154: =-CUMIPMT(F154/1200,300,O154,1,300,0) -> 225923.18 | N154: =O154+M154 -> 454523.18 | O154: =C154*(1-G154/100) -> 228600 | P154: 896.30265 | R154: =IF(H154="A","4",IF(H154="B","3",IF(H154="C","2",IF(H154="D","1",0)))) -> 1 | S154: =D154*0.4 +R154*0.3 +(1/(K154*0.3)) -> 896.3294
A155: North East | B155: Terraced | C155: 250000 | D155: 2200 | E155: 2024 | F155: 5.4 | G155: 6 | H155: D | I155: No | J155: First Timer | K155: =C155/D155 -> 113.63636 | L155: =PMT(F155/100/12, 300, -(C155 * (1 - G155/100))) -> 1429.1053 | M155: =-CUMIPMT(F155/1200,300,O155,1,300,0) -> 193731.59 | N155: =O155+M155 -> 428731.59 | O155: =C155*(1-G155/100) -> 235000 | P155: 880.30264 | R155: =IF(H155="A","4",IF(H155="B","3",IF(H155="C","2",IF(H155="D","1",0)))) -> 1 | S155: =D155*0.4 +R155*0.3 +(1/(K155*0.3)) -> 880.32933
A156: East of England | B156: Flat | C156: 290000 | D156: 2550 | E156: 2024 | F156: 5.2 | G156: 10 | H156: C | I156: No | J156: First Timer | K156: =C156/D156 -> 113.72549 | L156: =PMT(F156/100/12, 300, -(C156 * (1 - G156/100))) -> 1556.347 | M156: =-CUMIPMT(F156/1200,300,O156,1,300,0) -> 205904.09 | N156: =O156+M156 -> 466904.09 | O156: =C156*(1-G156/100) -> 261000 | P156: 1020.6026 | R156: =IF(H156="A","4",IF(H156="B","3",IF(H156="C","2",IF(H156="D","1",0)))) -> 2 | S156: =D156*0.4 +R156*0.3 +(1/(K156*0.3)) -> 1020.6293
A157: North West | B157: Terraced | C157: 265000 | D157: 2330 | E157: 2023 | F157: 6.3 | G157: 10 | H157: D | I157: No | J157: First Timer | K157: =C157/D157 -> 113.73391 | L157: =PMT(F157/100/12, 300, -(C157 * (1 - G157/100))) -> 1580.6908 | M157: =-CUMIPMT(F157/1200,300,O157,1,300,0) -> 235707.25 | N157: =O157+M157 -> 474207.25 | O157: =C157*(1-G157/100) -> 238500 | P157: 932.30264 | R157: =IF(H157="A","4",IF(H157="B","3",IF(H157="C","2",IF(H157="D","1",0)))) -> 1 | S157: =D157*0.4 +R157*0.3 +(1/(K157*0.3)) -> 932.32931
... A199: South East | B199: Flat | C199: 370000 | D199: 3000 | E199: 2024 | F199: 5.2 | G199: 12 | H199: C | I199: No | J199: First Timer | K199: =C199/D199 -> 123.33333 | L199: =PMT(F199/100/12, 300, -(C199 * (1 - G199/100))) -> 1941.5577 | M199: =-CUMIPMT(F199/1200,300,O199,1,300,0) -> 256867.32 | N199: =O199+M199 -> 582467.32 | O199: =C199*(1-G199/100) -> 325600 | P199: 1200.6024 | R199: =IF(H199="A","4",IF(H199="B","3",IF(H199="C","2",IF(H199="D","1",0)))) -> 2 | S199: =D199*0.4 +R199*0.3 +(1/(K199*0.3)) -> 1200.627
A200: East of England | B200: Flat | C200: 310000 | D200: 2510 | E200: 2024 | F200: 5.3 | G200: 10 | H200: C | I200: No | J200: First Timer | K200: =C200/D200 -> 123.50598 | L200: =PMT(F200/100/12, 300, -(C200 * (1 - G200/100))) -> 1680.1413 | M200: =-CUMIPMT(F200/1200,300,O200,1,300,0) -> 225042.4 | N200: =O200+M200 -> 504042.4 | O200: =C200*(1-G200/100) -> 279000 | P200: 1004.6024 | R200: =IF(H200="A","4",IF(H200="B","3",IF(H200="C","2",IF(H200="D","1",0)))) -> 2 | S200: =D200*0.4 +R200*0.3 +(1/(K200*0.3)) -> 1004.627
A201: South East | B201: Flat | C201: 372000 | D201: 3010 | E201: 2024 | F201: 5.2 | G201: 12 | H201: C | I201: No | J201: First Timer | K201: =C201/D201 -> 123.58804 | L201: =PMT(F201/100/12, 300, -(C201 * (1 - G201/100))) -> 1952.0527 | M201: =-CUMIPMT(F201/1200,300,O201,1,300,0) -> 258255.8 | N201: =O201+M201 -> 585615.8 | O201: =C201*(1-G201/100) -> 327360 | P201: 1204.6024 | R201: =IF(H201="A","4",IF(H201="B","3",IF(H201="C","2",IF(H201="D","1",0)))) -> 2 | S201: =D201*0.4 +R201*0.3 +(1/(K201*0.3)) -> 1204.627
A202: South East | B202: Flat | C202: 365000 | D202: 2950 | E202: 2024 | F202: 5.2 | G202: 12 | H202: C | I202: No | J202: First Timer | K202: =C202/D202 -> 123.72881 | L202: =PMT(F202/100/12, 300, -(C202 * (1 - G202/100))) -> 1915.3205 | M202: =-CUMIPMT(F202/1200,300,O202,1,300,0) -> 253396.14 | N202: =O202+M202 -> 574596.14 | O202: =C202*(1-G202/100) -> 321200 | P202: 1180.6024 | R202: =IF(H202="A","4",IF(H202="B","3",IF(H202="C","2",IF(H202="D","1",0)))) -> 2 | S202: =D202*0.4 +R202*0.3 +(1/(K202*0.3)) -> 1180.6269
A203: South East | B203: Flat | C203: 360000 | D203: 2900 | E203: 2024 | F203: 5.2 | G203: 12 | H203: C | I203: No | J203: First Timer | K203: =C203/D203 -> 124.13793 | L203: =PMT(F203/100/12, 300, -(C203 * (1 - G203/100))) -> 1889.0832 | M203: =-CUMIPMT(F203/1200,300,O203,1,300,0) -> 249924.96 | N203: =O203+M203 -> 566724.96 | O203: =C203*(1-G203/100) -> 316800 | P203: 1160.6024 | R203: =IF(H203="A","4",IF(H203="B","3",IF(H203="C","2",IF(H203="D","1",0)))) -> 2 | S203: =D203*0.4 +R203*0.3 +(1/(K203*0.3)) -> 1160.6269
A204: South East | B204: Flat | C204: 348000 | D204: 2800 | E204: 2024 | F204: 5.2 | G204: 12 | H204: C | I204: No | J204: First Timer | K204: =C204/D204 -> 124.28571 | L204: =PMT(F204/100/12, 300, -(C204 * (1 - G204/100))) -> 1826.1138 | M204: =-CUMIPMT(F204/1200,300,O204,1,300,0) -> 241594.13 | N204: =O204+M204 -> 547834.13 | O204: =C204*(1-G204/100) -> 306240 | P204: 1120.6024 | R204: =IF(H204="A","4",IF(H204="B","3",IF(H204="C","2",IF(H204="D","1",0)))) -> 2 | S204: =D204*0.4 +R204*0.3 +(1/(K204*0.3)) -> 1120.6268
A205: North East | B205: Terraced | C205: 240000 | D205: 1930 | E205: 2024 | F205: 5.3 | G205: 6 | H205: D | I205: No | J205: First Timer | K205: =C205/D205 -> 124.35233 | L205: =PMT(F205/100/12, 300, -(C205 * (1 - G205/100))) -> 1358.5659 | M205: =-CUMIPMT(F205/1200,300,O205,1,300,0) -> 181969.77 | N205: =O205+M205 -> 407569.77 | O205: =C205*(1-G205/100) -> 225600 | P205: 772.30241 | R205: =IF(H205="A","4",IF(H205="B","3",IF(H205="C","2",IF(H205="D","1",0)))) -> 1 | S205: =D205*0.4 +R205*0.3 +(1/(K205*0.3)) -> 772.32681
A206: South East | B206: Flat | C206: 345000 | D206: 2750 | E206: 2024 | F206: 5.2 | G206: 12 | H206: C | I206: No | J206: First Timer | K206: =C206/D206 -> 125.45455 | L206: =PMT(F206/100/12, 300, -(C206 * (1 - G206/100))) -> 1810.3714 | M206: =-CUMIPMT(F206/1200,300,O206,1,300,0) -> 239511.42 | N206: =O206+M206 -> 543111.42 | O206: =C206*(1-G206/100) -> 303600 | P206: 1100.6024 | R206: =IF(H206="A","4",IF(H206="B","3",IF(H206="C","2",IF(H206="D","1",0)))) -> 2 | S206: =D206*0.4 +R206*0.3 +(1/(K206*0.3)) -> 1100.6266
A207: North West | B207: Terraced | C207: 252000 | D207: 1990 | E207: 2023 | F207: 6.3 | G207: 10 | H207: D | I207: No | J207: First Timer | K207: =C207/D207 -> 126.63317 | L207: =PMT(F207/100/12, 300, -(C207 * (1 - G207/100))) -> 1503.1475 | M207: =-CUMIPMT(F207/1200,300,O207,1,300,0) -> 224144.25 | N207: =O207+M207 -> 450944.25 | O207: =C207*(1-G207/100) -> 226800 | P207: 796.30237 | R207: =IF(H207="A","4",IF(H207="B","3",IF(H207="C","2",IF(H207="D","1",0)))) -> 1 | S207: =D207*0.4 +R207*0.3 +(1/(K207*0.3)) -> 796.32632
A208: South East | B208: Flat | C208: 343000 | D208: 2700 | E208: 2024 | F208: 5.2 | G208: 12 | H208: C | I208: No | J208: First Timer | K208: =C208/D208 -> 127.03704 | L208: =PMT(F208/100/12, 300, -(C208 * (1 - G208/100))) -> 1799.8765 | M208: =-CUMIPMT(F208/1200,300,O208,1,300,0) -> 238122.95 | N208: =O208+M208 -> 539962.95 | O208: =C208*(1-G208/100) -> 301840 | P208: 1080.6024 | R208: =IF(H208="A","4",IF(H208="B","3",IF(H208="C","2",IF(H208="D","1",0)))) -> 2 | S208: =D208*0.4 +R208*0.3 +(1/(K208*0.3)) -> 1080.6262
A209: South East | B209: Flat | C209: 340000 | D209: 2650 | E209: 2024 | F209: 5.2 | G209: 12 | H209: C | I209: No | J209: First Timer | K209: =C209/D209 -> 128.30189 | L209: =PMT(F209/100/12, 300, -(C209 * (1 - G209/100))) -> 1784.1341 | M209: =-CUMIPMT(F209/1200,300,O209,1,300,0) -> 236040.24 | N209: =O209+M209 -> 535240.24 | O209: =C209*(1-G209/100) -> 299200 | P209: 1060.6023 | R209: =IF(H209="A","4",IF(H209="B","3",IF(H209="C","2",IF(H209="D","1",0)))) -> 2 | S209: =D209*0.4 +R209*0.3 +(1/(K209*0.3)) -> 1060.626
A210: South East | B210: Flat | C210: 310000 | D210: 2400 | E210: 2023 | F210: 6 | G210: 12 | H210: C | I210: No | J210: First Timer | K210: =C210/D210 -> 129.16667 | L210: =PMT(F210/100/12, 300, -(C210 * (1 - G210/100))) -> 1757.6542 | M210: =-CUMIPMT(F210/1200,300,O210,1,300,0) -> 254496.27 | N210: =O210+M210 -> 527296.27 | O210: =C210*(1-G210/100) -> 272800 | P210: 960.60232 | R210: =IF(H210="A","4",IF(H210="B","3",IF(H210="C","2",IF(H210="D","1",0)))) -> 2 | S210: =D210*0.4 +R210*0.3 +(1/(K210*0.3)) -> 960.62581
A211: East of England | B211: Flat | C211: 330000 | D211: 2510 | E211: 2024 | F211: 5.3 | G211: 10 | H211: C | I211: No | J211: First Timer | K211: =C211/D211 -> 131.4741 | L211: =PMT(F211/100/12, 300, -(C211 * (1 - G211/100))) -> 1788.5376 | M211: =-CUMIPMT(F211/1200,300,O211,1,300,0) -> 239561.27 | N211: =O211+M211 -> 536561.27 | O211: =C211*(1-G211/100) -> 297000 | P211: 1004.6023 | R211: =IF(H211="A","4",IF(H211="B","3",IF(H211="C","2",IF(H211="D","1",0)))) -> 2 | S211: =D211*0.4 +R211*0.3 +(1/(K211*0.3)) -> 1004.6254
A212: South East | B212: Flat | C212: 310000 | D212: 2350 | E212: 2024 | F212: 5.2 | G212: 12 | H212: C | I212: No | J212: First Timer | K212: =C212/D212 -> 131.91489 | L212: =PMT(F212/100/12, 300, -(C212 * (1 - G212/100))) -> 1626.7105 | M212: =-CUMIPMT(F212/1200,300,O212,1,300,0) -> 215213.16 | N212: =O212+M212 -> 488013.16 | O212: =C212*(1-G212/100) -> 272800 | P212: 940.60227 | R212: =IF(H212="A","4",IF(H212="B","3",IF(H212="C","2",IF(H212="D","1",0)))) -> 2 | S212: =D212*0.4 +R212*0.3 +(1/(K212*0.3)) -> 940.62527
A213: South East | B213: Flat | C213: 330000 | D213: 2500 | E213: 2024 | F213: 5.2 | G213: 12 | H213: C | I213: No | J213: First Timer | K213: =C213/D213 -> 132 | L213: =PMT(F213/100/12, 300, -(C213 * (1 - G213/100))) -> 1731.6596 | M213: =-CUMIPMT(F213/1200,300,O213,1,300,0) -> 229097.88 | N213: =O213+M213 -> 519497.88 | O213: =C213*(1-G213/100) -> 290400 | P213: 1000.6023 | R213: =IF(H213="A","4",IF(H213="B","3",IF(H213="C","2",IF(H213="D","1",0)))) -> 2 | S213: =D213*0.4 +R213*0.3 +(1/(K213*0.3)) -> 1000.6253
A214: South East | B214: Flat | C214: 320000 | D214: 2420 | E214: 2024 | F214: 5.2 | G214: 12 | H214: C | I214: No | J214: First Timer | K214: =C214/D214 -> 132.2314 | L214: =PMT(F214/100/12, 300, -(C214 * (1 - G214/100))) -> 1679.1851 | M214: =-CUMIPMT(F214/1200,300,O214,1,300,0) -> 222155.52 | N214: =O214+M214 -> 503755.52 | O214: =C214*(1-G214/100) -> 281600 | P214: 968.60227 | R214: =IF(H214="A","4",IF(H214="B","3",IF(H214="C","2",IF(H214="D","1",0)))) -> 2 | S214: =D214*0.4 +R214*0.3 +(1/(K214*0.3)) -> 968.62521
A215: South East | B215: Flat | C215: 315000 | D215: 2380 | E215: 2023 | F215: 6 | G215: 12 | H215: C | I215: No | J215: First Timer | K215: =C215/D215 -> 132.35294 | L215: =PMT(F215/100/12, 300, -(C215 * (1 - G215/100))) -> 1786.0035 | M215: =-CUMIPMT(F215/1200,300,O215,1,300,0) -> 258601.05 | N215: =O215+M215 -> 535801.05 | O215: =C215*(1-G215/100) -> 277200 | P215: 952.60227 | R215: =IF(H215="A","4",IF(H215="B","3",IF(H215="C","2",IF(H215="D","1",0)))) -> 2 | S215: =D215*0.4 +R215*0.3 +(1/(K215*0.3)) -> 952.62519
A216: South East | B216: Flat | C216: 318000 | D216: 2400 | E216: 2023 | F216: 6 | G216: 12 | H216: C | I216: No | J216: First Timer | K216: =C216/D216 -> 132.5 | L216: =PMT(F216/100/12, 300, -(C216 * (1 - G216/100))) -> 1803.013 | M216: =-CUMIPMT(F216/1200,300,O216,1,300,0) -> 261063.91 | N216: =O216+M216 -> 540903.91 | O216: =C216*(1-G216/100) -> 279840 | P216: 960.60226 | R216: =IF(H216="A","4",IF(H216="B","3",IF(H216="C","2",IF(H216="D","1",0)))) -> 2 | S216: =D216*0.4 +R216*0.3 +(1/(K216*0.3)) -> 960.62516
A217: South East | B217: Flat | C217: 325000 | D217: 2450 | E217: 2023 | F217: 6 | G217: 12 | H217: C | I217: No | J217: First Timer | K217: =C217/D217 -> 132.65306 | L217: =PMT(F217/100/12, 300, -(C217 * (1 - G217/100))) -> 1842.702 | M217: =-CUMIPMT(F217/1200,300,O217,1,300,0) -> 266810.6 | N217: =O217+M217 -> 552810.6 | O217: =C217*(1-G217/100) -> 286000 | P217: 980.60226 | R217: =IF(H217="A","4",IF(H217="B","3",IF(H217="C","2",IF(H217="D","1",0)))) -> 2 | S217: =D217*0.4 +R217*0.3 +(1/(K217*0.3)) -> 980.62513
A218: South East | B218: Flat | C218: 325000 | D218: 2450 | E218: 2024 | F218: 5.2 | G218: 12 | H218: C | I218: No | J218: First Timer | K218: =C218/D218 -> 132.65306 | L218: =PMT(F218/100/12, 300, -(C218 * (1 - G218/100))) -> 1705.4223 | M218: =-CUMIPMT(F218/1200,300,O218,1,300,0) -> 225626.7 | N218: =O218+M218 -> 511626.7 | O218: =C218*(1-G218/100) -> 286000 | P218: 980.60226 | R218: =IF(H218="A","4",IF(H218="B","3",IF(H218="C","2",IF(H218="D","1",0)))) -> 2 | S218: =D218*0.4 +R218*0.3 +(1/(K218*0.3)) -> 980.62513
A219: South East | B219: Flat | C219: 292000 | D219: 2190 | E219: 2023 | F219: 6 | G219: 12 | H219: C | I219: No | J219: First Timer | K219: =C219/D219 -> 133.33333 | L219: =PMT(F219/100/12, 300, -(C219 * (1 - G219/100))) -> 1655.5969 | M219: =-CUMIPMT(F219/1200,300,O219,1,300,0) -> 239719.06 | N219: =O219+M219 -> 496679.06 | O219: =C219*(1-G219/100) -> 256960 | P219: 876.60225 | R219: =IF(H219="A","4",IF(H219="B","3",IF(H219="C","2",IF(H219="D","1",0)))) -> 2 | S219: =D219*0.4 +R219*0.3 +(1/(K219*0.3)) -> 876.625
A220: South East | B220: Flat | C220: 300000 | D220: 2250 | E220: 2024 | F220: 5.2 | G220: 12 | H220: C | I220: No | J220: First Timer | K220: =C220/D220 -> 133.33333 | L220: =PMT(F220/100/12, 300, -(C220 * (1 - G220/100))) -> 1574.236 | M220: =-CUMIPMT(F220/1200,300,O220,1,300,0) -> 208270.8 | N220: =O220+M220 -> 472270.8 | O220: =C220*(1-G220/100) -> 264000 | P220: 900.60225 | R220: =IF(H220="A","4",IF(H220="B","3",IF(H220="C","2",IF(H220="D","1",0)))) -> 2 | S220: =D220*0.4 +R220*0.3 +(1/(K220*0.3)) -> 900.625
A221: South East | B221: Flat | C221: 340000 | D221: 2550 | E221: 2023 | F221: 6 | G221: 12 | H221: C | I221: No | J221: First Timer | K221: =C221/D221 -> 133.33333 | L221: =PMT(F221/100/12, 300, -(C221 * (1 - G221/100))) -> 1927.7498 | M221: =-CUMIPMT(F221/1200,300,O221,1,300,0) -> 279124.94 | N221: =O221+M221 -> 578324.94 | O221: =C221*(1-G221/100) -> 299200 | P221: 1020.6023 | R221: =IF(H221="A","4",IF(H221="B","3",IF(H221="C","2",IF(H221="D","1",0)))) -> 2 | S221: =D221*0.4 +R221*0.3 +(1/(K221*0.3)) -> 1020.625
A222: South East | B222: Flat | C222: 320000 | D222: 2400 | E222: 2024 | F222: 5.2 | G222: 12 | H222: C | I222: No | J222: First Timer | K222: =C222/D222 -> 133.33333 | L222: =PMT(F222/100/12, 300, -(C222 * (1 - G222/100))) -> 1679.1851 | M222: =-CUMIPMT(F222/1200,300,O222,1,300,0) -> 222155.52 | N222: =O222+M222 -> 503755.52 | O222: =C222*(1-G222/100) -> 281600 | P222: 960.60225 | R222: =IF(H222="A","4",IF(H222="B","3",IF(H222="C","2",IF(H222="D","1",0)))) -> 2 | S222: =D222*0.4 +R222*0.3 +(1/(K222*0.3)) -> 960.625
A223: South East | B223: Flat | C223: 310000 | D223: 2300 | E223: 2024 | F223: 5.2 | G223: 12 | H223: C | I223: No | J223: First Timer | K223: =C223/D223 -> 134.78261 | L223: =PMT(F223/100/12, 300, -(C223 * (1 - G223/100))) -> 1626.7105 | M223: =-CUMIPMT(F223/1200,300,O223,1,300,0) -> 215213.16 | N223: =O223+M223 -> 488013.16 | O223: =C223*(1-G223/100) -> 272800 | P223: 920.60223 | R223: =IF(H223="A","4",IF(H223="B","3",IF(H223="C","2",IF(H223="D","1",0)))) -> 2 | S223: =D223*0.4 +R223*0.3 +(1/(K223*0.3)) -> 920.62473
... A306: North West | B306: Semi Detached | C306: 298000 | D306: 1870 | E306: 2024 | F306: 5.4 | G306: 14 | H306: C | I306: No | J306: Upsizer | K306: =C306/D306 -> 159.35829 | L306: =PMT(F306/100/12, 300, -(C306 * (1 - G306/100))) -> 1558.5154 | M306: =-CUMIPMT(F306/1200,300,O306,1,300,0) -> 211274.61 | N306: =O306+M306 -> 467554.61 | O306: =C306*(1-G306/100) -> 256280 | P306: 748.60188 | R306: =IF(H306="A","4",IF(H306="B","3",IF(H306="C","2",IF(H306="D","1",0)))) -> 2 | S306: =D306*0.4 +R306*0.3 +(1/(K306*0.3)) -> 748.62092
A307: South West | B307: Terraced | C307: 360000 | D307: 2250 | E307: 2024 | F307: 5.3 | G307: 10 | H307: C | I307: No | J307: First Timer | K307: =C307/D307 -> 160 | L307: =PMT(F307/100/12, 300, -(C307 * (1 - G307/100))) -> 1951.1319 | M307: =-CUMIPMT(F307/1200,300,O307,1,300,0) -> 261339.56 | N307: =O307+M307 -> 585339.56 | O307: =C307*(1-G307/100) -> 324000 | P307: 900.60188 | R307: =IF(H307="A","4",IF(H307="B","3",IF(H307="C","2",IF(H307="D","1",0)))) -> 2 | S307: =D307*0.4 +R307*0.3 +(1/(K307*0.3)) -> 900.62083
A308: South West | B308: Terraced | C308: 322000 | D308: 2010 | E308: 2024 | F308: 5.3 | G308: 10 | H308: C | I308: No | J308: First Timer | K308: =C308/D308 -> 160.199 | L308: =PMT(F308/100/12, 300, -(C308 * (1 - G308/100))) -> 1745.1791 | M308: =-CUMIPMT(F308/1200,300,O308,1,300,0) -> 233753.72 | N308: =O308+M308 -> 523553.72 | O308: =C308*(1-G308/100) -> 289800 | P308: 804.60187 | R308: =IF(H308="A","4",IF(H308="B","3",IF(H308="C","2",IF(H308="D","1",0)))) -> 2 | S308: =D308*0.4 +R308*0.3 +(1/(K308*0.3)) -> 804.62081
A309: Yorkshire | B309: Semi Detached | C309: 345000 | D309: 2150 | E309: 2024 | F309: 5.5 | G309: 12 | H309: C | I309: No | J309: Upsizer | K309: =C309/D309 -> 160.46512 | L309: =PMT(F309/100/12, 300, -(C309 * (1 - G309/100))) -> 1864.3696 | M309: =-CUMIPMT(F309/1200,300,O309,1,300,0) -> 255710.89 | N309: =O309+M309 -> 559310.89 | O309: =C309*(1-G309/100) -> 303600 | P309: 860.60187 | R309: =IF(H309="A","4",IF(H309="B","3",IF(H309="C","2",IF(H309="D","1",0)))) -> 2 | S309: =D309*0.4 +R309*0.3 +(1/(K309*0.3)) -> 860.62077
A310: South West | B310: Terraced | C310: 326000 | D310: 2030 | E310: 2023 | F310: 6.1 | G310: 10 | H310: C | I310: No | J310: First Timer | K310: =C310/D310 -> 160.59113 | L310: =PMT(F310/100/12, 300, -(C310 * (1 - G310/100))) -> 1908.3558 | M310: =-CUMIPMT(F310/1200,300,O310,1,300,0) -> 279106.74 | N310: =O310+M310 -> 572506.74 | O310: =C310*(1-G310/100) -> 293400 | P310: 812.60187 | R310: =IF(H310="A","4",IF(H310="B","3",IF(H310="C","2",IF(H310="D","1",0)))) -> 2 | S310: =D310*0.4 +R310*0.3 +(1/(K310*0.3)) -> 812.62076
A311: South West | B311: Terraced | C311: 330000 | D311: 2050 | E311: 2024 | F311: 5.3 | G311: 10 | H311: C | I311: No | J311: First Timer | K311: =C311/D311 -> 160.97561 | L311: =PMT(F311/100/12, 300, -(C311 * (1 - G311/100))) -> 1788.5376 | M311: =-CUMIPMT(F311/1200,300,O311,1,300,0) -> 239561.27 | N311: =O311+M311 -> 536561.27 | O311: =C311*(1-G311/100) -> 297000 | P311: 820.60186 | R311: =IF(H311="A","4",IF(H311="B","3",IF(H311="C","2",IF(H311="D","1",0)))) -> 2 | S311: =D311*0.4 +R311*0.3 +(1/(K311*0.3)) -> 820.62071
A312: Yorkshire | B312: Semi Detached | C312: 330000 | D312: 2050 | E312: 2024 | F312: 5.5 | G312: 12 | H312: C | I312: No | J312: Upsizer | K312: =C312/D312 -> 160.97561 | L312: =PMT(F312/100/12, 300, -(C312 * (1 - G312/100))) -> 1783.3101 | M312: =-CUMIPMT(F312/1200,300,O312,1,300,0) -> 244593.02 | N312: =O312+M312 -> 534993.02 | O312: =C312*(1-G312/100) -> 290400 | P312: 820.60186 | R312: =IF(H312="A","4",IF(H312="B","3",IF(H312="C","2",IF(H312="D","1",0)))) -> 2 | S312: =D312*0.4 +R312*0.3 +(1/(K312*0.3)) -> 820.62071
A313: North West | B313: Semi Detached | C313: 330000 | D313: 2050 | E313: 2024 | F313: 5.4 | G313: 14 | H313: C | I313: No | J313: Upsizer | K313: =C313/D313 -> 160.97561 | L313: =PMT(F313/100/12, 300, -(C313 * (1 - G313/100))) -> 1725.8727 | M313: =-CUMIPMT(F313/1200,300,O313,1,300,0) -> 233961.81 | N313: =O313+M313 -> 517761.81 | O313: =C313*(1-G313/100) -> 283800 | P313: 820.60186 | R313: =IF(H313="A","4",IF(H313="B","3",IF(H313="C","2",IF(H313="D","1",0)))) -> 2 | S313: =D313*0.4 +R313*0.3 +(1/(K313*0.3)) -> 820.62071
A314: South West | B314: Terraced | C314: 335000 | D314: 2080 | E314: 2024 | F314: 5.3 | G314: 10 | H314: C | I314: No | J314: First Timer | K314: =C314/D314 -> 161.05769 | L314: =PMT(F314/100/12, 300, -(C314 * (1 - G314/100))) -> 1815.6366 | M314: =-CUMIPMT(F314/1200,300,O314,1,300,0) -> 243190.98 | N314: =O314+M314 -> 544690.98 | O314: =C314*(1-G314/100) -> 301500 | P314: 832.60186 | R314: =IF(H314="A","4",IF(H314="B","3",IF(H314="C","2",IF(H314="D","1",0)))) -> 2 | S314: =D314*0.4 +R314*0.3 +(1/(K314*0.3)) -> 832.6207
A315: Yorkshire | B315: Semi Detached | C315: 300000 | D315: 1860 | E315: 2024 | F315: 5.5 | G315: 12 | H315: C | I315: No | J315: Upsizer | K315: =C315/D315 -> 161.29032 | L315: =PMT(F315/100/12, 300, -(C315 * (1 - G315/100))) -> 1621.191 | M315: =-CUMIPMT(F315/1200,300,O315,1,300,0) -> 222357.29 | N315: =O315+M315 -> 486357.29 | O315: =C315*(1-G315/100) -> 264000 | P315: 744.60186 | R315: =IF(H315="A","4",IF(H315="B","3",IF(H315="C","2",IF(H315="D","1",0)))) -> 2 | S315: =D315*0.4 +R315*0.3 +(1/(K315*0.3)) -> 744.62067
A316: Yorkshire | B316: Semi Detached | C316: 320000 | D316: 1980 | E316: 2023 | F316: 6.2 | G316: 15 | H316: C | I316: No | J316: Upsizer | K316: =C316/D316 -> 161.61616 | L316: =PMT(F316/100/12, 300, -(C316 * (1 - G316/100))) -> 1785.9033 | M316: =-CUMIPMT(F316/1200,300,O316,1,300,0) -> 263770.99 | N316: =O316+M316 -> 535770.99 | O316: =C316*(1-G316/100) -> 272000 | P316: 792.60186 | R316: =IF(H316="A","4",IF(H316="B","3",IF(H316="C","2",IF(H316="D","1",0)))) -> 2 | S316: =D316*0.4 +R316*0.3 +(1/(K316*0.3)) -> 792.62063
A317: South West | B317: Terraced | C317: 340000 | D317: 2100 | E317: 2023 | F317: 6.1 | G317: 10 | H317: C | I317: No | J317: First Timer | K317: =C317/D317 -> 161.90476 | L317: =PMT(F317/100/12, 300, -(C317 * (1 - G317/100))) -> 1990.3097 | M317: =-CUMIPMT(F317/1200,300,O317,1,300,0) -> 291092.91 | N317: =O317+M317 -> 597092.91 | O317: =C317*(1-G317/100) -> 306000 | P317: 840.60185 | R317: =IF(H317="A","4",IF(H317="B","3",IF(H317="C","2",IF(H317="D","1",0)))) -> 2 | S317: =D317*0.4 +R317*0.3 +(1/(K317*0.3)) -> 840.62059
A318: Yorkshire | B318: Semi Detached | C318: 340000 | D318: 2100 | E318: 2024 | F318: 5.4 | G318: 15 | H318: C | I318: No | J318: Upsizer | K318: =C318/D318 -> 161.90476 | L318: =PMT(F318/100/12, 300, -(C318 * (1 - G318/100))) -> 1757.4955 | M318: =-CUMIPMT(F318/1200,300,O318,1,300,0) -> 238248.64 | N318: =O318+M318 -> 527248.64 | O318: =C318*(1-G318/100) -> 289000 | P318: 840.60185 | R318: =IF(H318="A","4",IF(H318="B","3",IF(H318="C","2",IF(H318="D","1",0)))) -> 2 | S318: =D318*0.4 +R318*0.3 +(1/(K318*0.3)) -> 840.62059
A319: Yorkshire | B319: Semi Detached | C319: 312000 | D319: 1920 | E319: 2024 | F319: 5.5 | G319: 12 | H319: C | I319: No | J319: Upsizer | K319: =C319/D319 -> 162.5 | L319: =PMT(F319/100/12, 300, -(C319 * (1 - G319/100))) -> 1686.0386 | M319: =-CUMIPMT(F319/1200,300,O319,1,300,0) -> 231251.59 | N319: =O319+M319 -> 505811.59 | O319: =C319*(1-G319/100) -> 274560 | P319: 768.60185 | R319: =IF(H319="A","4",IF(H319="B","3",IF(H319="C","2",IF(H319="D","1",0)))) -> 2 | S319: =D319*0.4 +R319*0.3 +(1/(K319*0.3)) -> 768.62051
A320: Yorkshire | B320: Semi Detached | C320: 325000 | D320: 2000 | E320: 2024 | F320: 5.5 | G320: 12 | H320: C | I320: No | J320: Upsizer | K320: =C320/D320 -> 162.5 | L320: =PMT(F320/100/12, 300, -(C320 * (1 - G320/100))) -> 1756.2902 | M320: =-CUMIPMT(F320/1200,300,O320,1,300,0) -> 240887.07 | N320: =O320+M320 -> 526887.07 | O320: =C320*(1-G320/100) -> 286000 | P320: 800.60185 | R320: =IF(H320="A","4",IF(H320="B","3",IF(H320="C","2",IF(H320="D","1",0)))) -> 2 | S320: =D320*0.4 +R320*0.3 +(1/(K320*0.3)) -> 800.62051
A321: North West | B321: Semi Detached | C321: 325000 | D321: 2000 | E321: 2024 | F321: 5.4 | G321: 14 | H321: C | I321: No | J321: Upsizer | K321: =C321/D321 -> 162.5 | L321: =PMT(F321/100/12, 300, -(C321 * (1 - G321/100))) -> 1699.7231 | M321: =-CUMIPMT(F321/1200,300,O321,1,300,0) -> 230416.94 | N321: =O321+M321 -> 509916.94 | O321: =C321*(1-G321/100) -> 279500 | P321: 800.60185 | R321: =IF(H321="A","4",IF(H321="B","3",IF(H321="C","2",IF(H321="D","1",0)))) -> 2 | S321: =D321*0.4 +R321*0.3 +(1/(K321*0.3)) -> 800.62051
A322: South West | B322: Terraced | C322: 345000 | D322: 2120 | E322: 2024 | F322: 5.3 | G322: 10 | H322: C | I322: No | J322: First Timer | K322: =C322/D322 -> 162.73585 | L322: =PMT(F322/100/12, 300, -(C322 * (1 - G322/100))) -> 1869.8347 | M322: =-CUMIPMT(F322/1200,300,O322,1,300,0) -> 250450.41 | N322: =O322+M322 -> 560950.41 | O322: =C322*(1-G322/100) -> 310500 | P322: 848.60184 | R322: =IF(H322="A","4",IF(H322="B","3",IF(H322="C","2",IF(H322="D","1",0)))) -> 2 | S322: =D322*0.4 +R322*0.3 +(1/(K322*0.3)) -> 848.62048
A323: South West | B323: Terraced | C323: 350000 | D323: 2150 | E323: 2023 | F323: 6.1 | G323: 10 | H323: C | I323: No | J323: First Timer | K323: =C323/D323 -> 162.7907 | L323: =PMT(F323/100/12, 300, -(C323 * (1 - G323/100))) -> 2048.8482 | M323: =-CUMIPMT(F323/1200,300,O323,1,300,0) -> 299654.47 | N323: =O323+M323 -> 614654.47 | O323: =C323*(1-G323/100) -> 315000 | P323: 860.60184 | R323: =IF(H323="A","4",IF(H323="B","3",IF(H323="C","2",IF(H323="D","1",0)))) -> 2 | S323: =D323*0.4 +R323*0.3 +(1/(K323*0.3)) -> 860.62048
A324: East of England | B324: Terraced | C324: 350000 | D324: 2150 | E324: 2024 | F324: 5.3 | G324: 10 | H324: C | I324: No | J324: First Timer | K324: =C324/D324 -> 162.7907 | L324: =PMT(F324/100/12, 300, -(C324 * (1 - G324/100))) -> 1896.9338 | M324: =-CUMIPMT(F324/1200,300,O324,1,300,0) -> 254080.13 | N324: =O324+M324 -> 569080.13 | O324: =C324*(1-G324/100) -> 315000 | P324: 860.60184 | R324: =IF(H324="A","4",IF(H324="B","3",IF(H324="C","2",IF(H324="D","1",0)))) -> 2 | S324: =D324*0.4 +R324*0.3 +(1/(K324*0.3)) -> 860.62048
A325: South West | B325: Terraced | C325: 355000 | D325: 2180 | E325: 2024 | F325: 5.3 | G325: 10 | H325: C | I325: No | J325: First Timer | K325: =C325/D325 -> 162.84404 | L325: =PMT(F325/100/12, 300, -(C325 * (1 - G325/100))) -> 1924.0328 | M325: =-CUMIPMT(F325/1200,300,O325,1,300,0) -> 257709.85 | N325: =O325+M325 -> 577209.85 | O325: =C325*(1-G325/100) -> 319500 | P325: 872.60184 | R325: =IF(H325="A","4",IF(H325="B","3",IF(H325="C","2",IF(H325="D","1",0)))) -> 2 | S325: =D325*0.4 +R325*0.3 +(1/(K325*0.3)) -> 872.62047
A326: Yorkshire | B326: Semi Detached | C326: 318000 | D326: 1950 | E326: 2024 | F326: 5.5 | G326: 12 | H326: C | I326: No | J326: Upsizer | K326: =C326/D326 -> 163.07692 | L326: =PMT(F326/100/12, 300, -(C326 * (1 - G326/100))) -> 1718.4624 | M326: =-CUMIPMT(F326/1200,300,O326,1,300,0) -> 235698.73 | N326: =O326+M326 -> 515538.73 | O326: =C326*(1-G326/100) -> 279840 | P326: 780.60184 | R326: =IF(H326="A","4",IF(H326="B","3",IF(H326="C","2",IF(H326="D","1",0)))) -> 2 | S326: =D326*0.4 +R326*0.3 +(1/(K326*0.3)) -> 780.62044
A327: Yorkshire | B327: Semi Detached | C327: 298000 | D327: 1820 | E327: 2023 | F327: 6.3 | G327: 12 | H327: C | I327: No | J327: Upsizer | K327: =C327/D327 -> 163.73626 | L327: =PMT(F327/100/12, 300, -(C327 * (1 - G327/100))) -> 1738.0309 | M327: =-CUMIPMT(F327/1200,300,O327,1,300,0) -> 259169.26 | N327: =O327+M327 -> 521409.26 | O327: =C327*(1-G327/100) -> 262240 | P327: 728.60183 | R327: =IF(H327="A","4",IF(H327="B","3",IF(H327="C","2",IF(H327="D","1",0)))) -> 2 | S327: =D327*0.4 +R327*0.3 +(1/(K327*0.3)) -> 728.62036
A328: London | B328: Flat | C328: 475000 | D328: 2900 | E328: 2024 | F328: 5 | G328: 12 | H328: C | I328: No | J328: First Timer | K328: =C328/D328 -> 163.7931 | L328: =PMT(F328/100/12, 300, -(C328 * (1 - G328/100))) -> 2443.5864 | M328: =-CUMIPMT(F328/1200,300,O328,1,300,0) -> 315075.91 | N328: =O328+M328 -> 733075.91 | O328: =C328*(1-G328/100) -> 418000 | P328: 1160.6018 | R328: =IF(H328="A","4",IF(H328="B","3",IF(H328="C","2",IF(H328="D","1",0)))) -> 2 | S328: =D328*0.4 +R328*0.3 +(1/(K328*0.3)) -> 1160.6204
A329: East Midlands | B329: Semi Detached | C329: 385000 | D329: 2350 | E329: 2024 | F329: 5.3 | G329: 18 | H329: B | I329: No | J329: Upsizer | K329: =C329/D329 -> 163.82979 | L329: =PMT(F329/100/12, 300, -(C329 * (1 - G329/100))) -> 1901.1492 | M329: =-CUMIPMT(F329/1200,300,O329,1,300,0) -> 254644.75 | N329: =O329+M329 -> 570344.75 | O329: =C329*(1-G329/100) -> 315700 | P329: 940.90183 | R329: =IF(H329="A","4",IF(H329="B","3",IF(H329="C","2",IF(H329="D","1",0)))) -> 3 | S329: =D329*0.4 +R329*0.3 +(1/(K329*0.3)) -> 940.92035
A330: North West | B330: Semi Detached | C330: 320000 | D330: 1950 | E330: 2024 | F330: 5.4 | G330: 14 | H330: C | I330: No | J330: Upsizer | K330: =C330/D330 -> 164.10256 | L330: =PMT(F330/100/12, 300, -(C330 * (1 - G330/100))) -> 1673.5735 | M330: =-CUMIPMT(F330/1200,300,O330,1,300,0) -> 226872.06 | N330: =O330+M330 -> 502072.06 | O330: =C330*(1-G330/100) -> 275200 | P330: 780.60183 | R330: =IF(H330="A","4",IF(H330="B","3",IF(H330="C","2",IF(H330="D","1",0)))) -> 2 | S330: =D330*0.4 +R330*0.3 +(1/(K330*0.3)) -> 780.62031
A331: Yorkshire | B331: Semi Detached | C331: 325000 | D331: 1980 | E331: 2023 | F331: 6.2 | G331: 15 | H331: C | I331: No | J331: Upsizer | K331: =C331/D331 -> 164.14141 | L331: =PMT(F331/100/12, 300, -(C331 * (1 - G331/100))) -> 1813.808 | M331: =-CUMIPMT(F331/1200,300,O331,1,300,0) -> 267892.41 | N331: =O331+M331 -> 544142.41 | O331: =C331*(1-G331/100) -> 276250 | P331: 792.60183 | R331: =IF(H331="A","4",IF(H331="B","3",IF(H331="C","2",IF(H331="D","1",0)))) -> 2 | S331: =D331*0.4 +R331*0.3 +(1/(K331*0.3)) -> 792.62031
A332: East of England | B332: Terraced | C332: 345000 | D332: 2100 | E332: 2024 | F332: 5.3 | G332: 10 | H332: C | I332: No | J332: First Timer | K332: =C332/D332 -> 164.28571 | L332: =PMT(F332/100/12, 300, -(C332 * (1 - G332/100))) -> 1869.8347 | M332: =-CUMIPMT(F332/1200,300,O332,1,300,0) -> 250450.41 | N332: =O332+M332 -> 560950.41 | O332: =C332*(1-G332/100) -> 310500 | P332: 840.60183 | R332: =IF(H332="A","4",IF(H332="B","3",IF(H332="C","2",IF(H332="D","1",0)))) -> 2 | S332: =D332*0.4 +R332*0.3 +(1/(K332*0.3)) -> 840.62029
A333: North West | B333: Semi Detached | C333: 305000 | D333: 1850 | E333: 2024 | F333: 5.4 | G333: 14 | H333: C | I333: No | J333: First Timer | K333: =C333/D333 -> 164.86486 | L333: =PMT(F333/100/12, 300, -(C333 * (1 - G333/100))) -> 1595.1248 | M333: =-CUMIPMT(F333/1200,300,O333,1,300,0) -> 216237.43 | N333: =O333+M333 -> 478537.43 | O333: =C333*(1-G333/100) -> 262300 | P333: 740.60182 | R333: =IF(H333="A","4",IF(H333="B","3",IF(H333="C","2",IF(H333="D","1",0)))) -> 2 | S333: =D333*0.4 +R333*0.3 +(1/(K333*0.3)) -> 740.62022
A334: North West | B334: Semi Detached | C334: 330000 | D334: 2000 | E334: 2023 | F334: 6.3 | G334: 14 | H334: C | I334: No | J334: Upsizer | K334: =C334/D334 -> 165 | L334: =PMT(F334/100/12, 300, -(C334 * (1 - G334/100))) -> 1880.9227 | M334: =-CUMIPMT(F334/1200,300,O334,1,300,0) -> 280476.8 | N334: =O334+M334 -> 564276.8 | O334: =C334*(1-G334/100) -> 283800 | P334: 800.60182 | R334: =IF(H334="A","4",IF(H334="B","3",IF(H334="C","2",IF(H334="D","1",0)))) -> 2 | S334: =D334*0.4 +R334*0.3 +(1/(K334*0.3)) -> 800.6202
A335: North East | B335: Semi Detached | C335: 278000 | D335: 1680 | E335: 2024 | F335: 5.4 | G335: 12 | H335: C | I335: No | J335: Upsizer | K335: =C335/D335 -> 165.47619 | L335: =PMT(F335/100/12, 300, -(C335 * (1 - G335/100))) -> 1487.729 | M335: =-CUMIPMT(F335/1200,300,O335,1,300,0) -> 201678.71 | N335: =O335+M335 -> 446318.71 | O335: =C335*(1-G335/100) -> 244640 | P335: 672.60181 | R335: =IF(H335="A","4",IF(H335="B","3",IF(H335="C","2",IF(H335="D","1",0)))) -> 2 | S335: =D335*0.4 +R335*0.3 +(1/(K335*0.3)) -> 672.62014
A336: Yorkshire | B336: Semi Detached | C336: 305000 | D336: 1840 | E336: 2024 | F336: 5.2 | G336: 15 | H336: C | I336: No | J336: Upsizer | K336: =C336/D336 -> 165.76087 | L336: =PMT(F336/100/12, 300, -(C336 * (1 - G336/100))) -> 1545.9117 | M336: =-CUMIPMT(F336/1200,300,O336,1,300,0) -> 204523.51 | N336: =O336+M336 -> 463773.51 | O336: =C336*(1-G336/100) -> 259250 | P336: 736.60181 | R336: =IF(H336="A","4",IF(H336="B","3",IF(H336="C","2",IF(H336="D","1",0)))) -> 2 | S336: =D336*0.4 +R336*0.3 +(1/(K336*0.3)) -> 736.62011
A337: South West | B337: Terraced | C337: 340000 | D337: 2050 | E337: 2024 | F337: 5.3 | G337: 10 | H337: C | I337: No | J337: First Timer | K337: =C337/D337 -> 165.85366 | L337: =PMT(F337/100/12, 300, -(C337 * (1 - G337/100))) -> 1842.7357 | M337: =-CUMIPMT(F337/1200,300,O337,1,300,0) -> 246820.7 | N337: =O337+M337 -> 552820.7 | O337: =C337*(1-G337/100) -> 306000 | P337: 820.60181 | R337: =IF(H337="A","4",IF(H337="B","3",IF(H337="C","2",IF(H337="D","1",0)))) -> 2 | S337: =D337*0.4 +R337*0.3 +(1/(K337*0.3)) -> 820.6201
A338: East of England | B338: Terraced | C338: 340000 | D338: 2050 | E338: 2024 | F338: 5.3 | G338: 10 | H338: C | I338: No | J338: First Timer | K338: =C338/D338 -> 165.85366 | L338: =PMT(F338/100/12, 300, -(C338 * (1 - G338/100))) -> 1842.7357 | M338: =-CUMIPMT(F338/1200,300,O338,1,300,0) -> 246820.7 | N338: =O338+M338 -> 552820.7 | O338: =C338*(1-G338/100) -> 306000 | P338: 820.60181 | R338: =IF(H338="A","4",IF(H338="B","3",IF(H338="C","2",IF(H338="D","1",0)))) -> 2 | S338: =D338*0.4 +R338*0.3 +(1/(K338*0.3)) -> 820.6201
A339: South West | B339: Terraced | C339: 345000 | D339: 2080 | E339: 2024 | F339: 5.3 | G339: 10 | H339: C | I339: No | J339: First Timer | K339: =C339/D339 -> 165.86538 | L339: =PMT(F339/100/12, 300, -(C339 * (1 - G339/100))) -> 1869.8347 | M339: =-CUMIPMT(F339/1200,300,O339,1,300,0) -> 250450.41 | N339: =O339+M339 -> 560950.41 | O339: =C339*(1-G339/100) -> 310500 | P339: 832.60181 | R339: =IF(H339="A","4",IF(H339="B","3",IF(H339="C","2",IF(H339="D","1",0)))) -> 2 | S339: =D339*0.4 +R339*0.3 +(1/(K339*0.3)) -> 832.6201
...

Sheet Average_price by region
A3: Region | B3: Average of Average_Price | E3: =(B6-B7)/B7 -> 1.729745
A4: East Midlands | B4: 326625
A5: East of England | B5: 448712.64
A6: London | B6: 653520
A7: North East | B7: 239406.98
A8: North West | B8: 298952.38
A9: South East | B9: 474319.59
A10: South West | B10: 418697.67
A11: West Midlands | B11: 361305.88
A12: Yorkshire | B12: 323627.91
A13: Grand Total | B13: 399742.18

Sheet Sales_volume
A3: Property_Type | B3: Average of Sales_Volume | C3: Sum of Average_Price
A4: Detached | B4: 1608.3333 | C4: 129502000 | E4: =C4/231 -> 560614.72
A5: Flat | B5: 2332.4885 | C5: 62637000
A6: Semi Detached | B6: 1915.7273 | C6: 62998000
A7: Terraced | B7: 1994.8387 | C7: 64257000
A8: Grand Total | B8: 1958.4606 | C8: 319394000
A23: Property_Type | B23: Average of Average_Price
A24: Detached | B24: 560614.72
A25: Flat | B25: 288649.77
A26: Semi Detached | B26: 381806.06
A27: Terraced | B27: 345467.74
A28: Grand Total | B28: 399742.18

Sheet Property_average_price by regio
A3: Average of Average_Price | B3: Year
A4: Region | B4: 2023 | C4: 2024 | D4: Grand Total | E4: Grow rate
A5: East Midlands | B5: 317478.26 | C5: 329861.54 | D5: 326625 | E5: =(C5-B5)/B5 -> 0.03900512
A6: East of England | B6: 427736.84 | C6: 454573.53 | D6: 448712.64 | E6: =(C6-B6)/B6 -> 0.062741117
A7: London | B7: 635090.91 | C7: 658717.95 | D7: 653520 | E7: =(C7-B7)/B7 -> 0.03720261
A8: North East | B8: 251344.83 | C8: 233333.33 | D8: 239406.98 | E8: =(C8-B8)/B8 -> -0.071660493
A9: North West | B9: 273173.91 | C9: 308672.13 | D9: 298952.38 | E9: =(C9-B9)/B9 -> 0.12994732
A10: South East | B10: 434130.43 | C10: 486810.81 | D10: 474319.59 | E10: =(C10-B10)/B10 -> 0.12134689
A11: South West | B11: 419000 | C11: 418623.19 | D11: 418697.67 | E11: =(C11-B11)/B11 -> -0.00089931168
A12: West Midlands | B12: 343074.07 | C12: 369793.1 | D12: 361305.88 | E12: =(C12-B12)/B12 -> 0.077881226
A13: Yorkshire | B13: 306142.86 | C13: 332068.97 | D13: 323627.91 | E13: =(C13-B13)/B13 -> 0.084686308
A14: Grand Total | B14: 369270.14 | C14: 410676.87 | D14: 399742.18
C16: =(C14-B14)/B14 -> 0.11213127 | E16: =(C7-C8)/C7 -> 0.64577657

Sheet Property_growth_rate
A3: Average of Average_Price | B3: Year
A4: Property_Type | B4: 2023 | C4: 2024 | D4: Grand Total
A5: Detached | B5: 521280.7 | C5: 573500 | D5: 560614.72
A6: Flat | B6: 270920.63 | C6: 295902.6 | D6: 288649.77
A7: Semi Detached | B7: 364378.38 | C7: 386843.75 | D7: 381806.06
A8: Terraced | B8: 326907.41 | C8: 353060.61 | D8: 345467.74
A9: Grand Total | B9: 369270.14 | C9: 410676.87 | D9: 399742.18
B12: 2023 | C12: 2024
A13: Detached | B13: 521280.7 | C13: 573500 | D13: =(C13-B13)/B13 -> 0.10017501
A14: Flat | B14: 270920.63 | C14: 295902.6 | D14: =(C14-B14)/B14 -> 0.092211368
A15: Semi Detached | B15: 364378.38 | C15: 386843.75 | D15: =(C15-B15)/B15 -> 0.061653965
A16: Terraced | B16: 326907.41 | C16: 353060.61 | D16: =(C16-B16)/B16 -> 0.080001854

Sheet Dashboard

Sheet Sheet6
A3: Region | B3: Average of Affordability_Index
A4: East Midlands | B4: 225.10602
A5: East of England | B5: 261.68975
A6: London | B6: 359.72056
A7: North East | B7: 144.30476
A8: North West | B8: 172.01107
A9: South East | B9: 277.63699
A10: South West | B10: 268.27738
A11: West Midlands | B11: 235.65145
A12: Yorkshire | B12: 241.03384
A13: Grand Total | B13: 245.51872

Sheet Mortgage_model

Sheet Sheet7
A3: Region | B3: Average of Monthly_Mortgage_cost
A4: East Midlands | B4: 1743.8925
A5: East of England | B5: 2272.3082
A6: London | B6: 3280.8675
A7: North East | B7: 1363.5604
A8: North West | B8: 1646.0601
A9: South East | B9: 2402.5528
A10: South West | B10: 2126.4191
A11: West Midlands | B11: 1901.3801
A12: Yorkshire | B12: 1728.458
A13: Grand Total | B13: 2078.7981
B17: =(B6-B7)/B7 -> 1.4061036

Sheet Sheet8
B3: Property_Type | C3: Values
B4: Detached | D4: Flat | F4: Semi Detached | H4: Terraced | J4: Total Average of Sales_Volume | K4: Total Average of Average_Price
A5: Buyer_Type | B5: Average of Sales_Volume | C5: Average of Average_Price | D5: Average of Sales_Volume | E5: Average of Average_Price | F5: Average of Sales_Volume | G5: Average of Average_Price | H5: Average of Sales_Volume | I5: Average of Average_Price
A6: First Timer | D6: 2330.787 | E6: 287879.63 | F6: 1850 | G6: 305000 | H6: 1942.4359 | I6: 296544.87 | J6: 2167.0777 | K6: 291549.6
A7: Investor | B7: 1603.8177 | C7: 574103.45 | J7: 1603.8177 | K7: 574103.45
A8: Upsizer | B8: 1641.0714 | C8: 462821.43 | D8: 2700 | E8: 455000 | F8: 1916.128 | G8: 382274.39 | H8: 2267.3333 | I8: 599866.67 | J8: 1932.3543 | K8: 421986.55
A9: Grand Total | B9: 1608.3333 | C9: 560614.72 | D9: 2332.4885 | E9: 288649.77 | F9: 1915.7273 | G9: 381806.06 | H9: 1994.8387 | I9: 345467.74 | J9: 1958.4606 | K9: 399742.18

Sheet Sheet9
A3: Count of Sales_Volume | B3: Property_Type
A4: Buyer_Type | B4: Detached | C4: Flat | D4: Semi Detached | E4: Terraced | F4: Grand Total
A5: First Timer | C5: 216 | D5: 1 | E5: 156 | F5: 373
A6: Investor | B6: 203 | F6: 203
A7: Upsizer | B7: 28 | C7: 1 | D7: 164 | E7: 30 | F7: 223
A8: Grand Total | B8: 231 | C8: 217 | D8: 165 | E8: 186 | F8: 799

Sheet Sheet13

Sheet Sheet10
A3: Average of Average_Price | B3: Property_Type
A4: Buyer_Type | B4: Detached | C4: Flat | D4: Semi Detached | E4: Terraced | F4: Grand Total
A5: First Timer | C5: 287879.63 | D5: 305000 | E5: 296544.87 | F5: 291549.6
A6: Investor | B6: 574103.45 | F6: 574103.45
A7: Upsizer | B7: 462821.43 | C7: 455000 | D7: 382274.39 | E7: 599866.67 | F7: 421986.55
A8: Grand Total | B8: 560614.72 | C8: 288649.77 | D8: 381806.06 | E8: 345467.74 | F8: 399742.18

Sheet Sheet11
G2: A | H2: =E4/E8 -> 0.0011473861
A3: Energy_Rating | B3: Average of Average_Price | C3: Average of Sales_Volume | H3: =E5/E8 -> 0.0011239753
A4: A | B4: 745852.94 | C4: 1795.4412 | E4: 1795.4412 | H4: =E6/E8 -> 0.0013266456
A5: B | B5: 475277.58 | C5: 1758.8078 | E5: 1758.8078 | H5: =E7/E8 -> 0.0013686188
A6: C | B6: 348000 | C6: 2075.9483 | E6: 2075.9483
A7: D | B7: 249481.65 | C7: 2141.6284 | E7: 2141.6284
A8: Grand Total | B8: 399742.18 | C8: 1958.4606 | E8: 1564810

Sheet Sheet12
A3: Region | B3: Average of Investment_Score
A4: East Midlands | B4: 742.4973
A5: East of England | B5: 783.63134
A6: London | B6: 886.16712
A7: North East | B7: 779.04445
A8: North West | B8: 850.79866
A9: South East | B9: 833.42824
A10: South West | B10: 711.26529
A11: West Midlands | B11: 749.19823
A12: Yorkshire | B12: 699.69713
A13: Grand Total | B13: 784.06066

Sheet Sheet14
A3: Average of Average_Price | B3: Property_Type
A4: Region | B4: Detached | C4: Flat | D4: Semi Detached | E4: Terraced | F4: Grand Total
A5: East Midlands | B5: 439500 | C5: 255812.5 | D5: 367954.55 | E5: 301666.67 | F5: 326625
A6: East of England | B6: 568972.22 | C6: 300000 | D6: 432388.89 | E6: 362285.71 | F6: 448712.64
A7: London | B7: 853513.51 | C7: 478060.61 | E7: 599866.67 | F7: 653520
A8: North East | B8: 350714.29 | C8: 201222.22 | D8: 285916.67 | E8: 240612.9 | F8: 239406.98
A9: North West | B9: 407142.86 | C9: 226666.67 | D9: 332633.33 | E9: 282862.07 | F9: 298952.38
A10: South East | B10: 622593.75 | C10: 329461.54 | D10: 463062.5 | E10: 386000 | F10: 474319.59
A11: South West | B11: 515419.35 | C11: 284285.71 | D11: 401464.29 | E11: 339950 | F11: 418697.67
A12: West Midlands | B12: 485531.25 | C12: 258166.67 | D12: 356142.86 | E12: 308500 | F12: 361305.88
A13: Yorkshire | B13: 414060.61 | C13: 209375 | D13: 322375 | E13: 269523.81 | F13: 323627.91
A14: Grand Total | B14: 560614.72 | C14: 288649.77 | D14: 381806.06 | E14: 345467.74 | F14: 399742.18

Sheet Sheet15
A3: Year | B3: Region | C3: Average of Average_Price
A4: 2023 | B4: East Midlands | C4: 317478.26
B5: East of England | C5: 427736.84
B6: London | C6: 635090.91
B7: North East | C7: 251344.83
B8: North West | C8: 273173.91
B9: South East | C9: 434130.43
B10: South West | C10: 419000
B11: West Midlands | C11: 343074.07
B12: Yorkshire | C12: 306142.86
A13: 2023 Total | C13: 369270.14
A14: 2024 | B14: East Midlands | C14: 329861.54
B15: East of England | C15: 454573.53
B16: London | C16: 658717.95
B17: North East | C17: 233333.33
B18: North West | C18: 308672.13
B19: South East | C19: 486810.81
B20: South West | C20: 418623.19
B21: West Midlands | C21: 369793.1
B22: Yorkshire | C22: 332068.97
A23: 2024 Total | C23: 410676.87
A24: Grand Total | C24: 399742.18

Sheet Sheet16
A3: Region | B3: Average of Sales_Volume
A4: East Midlands | B4: 1854.7727
A5: East of England | B5: 1957.1264
A6: London | B6: 2213.15
A7: North East | B7: 1946.6279
A8: North West | B8: 2125.8929
A9: South East | B9: 2081.3402
A10: South West | B10: 1776.1628
A11: West Midlands | B11: 1871.4118
A12: Yorkshire | B12: 1747.7907
A13: Grand Total | B13: 1958.4606

Sheet Sheet17
A3: Region | B3: Average of Investment_Score_1
A4: East Midlands | B4: 742.51591
A5: East of England | B5: 783.64606
A6: London | B6: 886.17843
A7: North East | B7: 779.07067
A8: North West | B8: 850.8212
A9: South East | B9: 833.44275
A10: South West | B10: 711.27885
A11: West Midlands | B11: 749.21601
A12: Yorkshire | B12: 699.71511
A13: (blank)
A14: Grand Total | B14: 784.07797

Sheet Sheet4
E1: =(C4+D4)/2 -> 371379.21
C3: 2023 | D3: 2024
B4: Detached | C4: =AVERAGE(Copy!C2:C528) -> 341779.89 | D4: =AVERAGE(Copy!C7:C798) -> 400978.54 | E4: =(D4-C4)/C4 -> 0.17320694
B5: Semi Detached | C5: =AVERAGE(Copy!C31:C532) -> 350350.6 | D5: =AVERAGE(Copy!C5:C800) -> 400507.54 | E5: =(D5-C5)/C5 -> 0.14316214
B6: Flat | C6: =AVERAGE(Copy!C6:C533) -> 343164.77 | D6: =AVERAGE(Copy!C3:C795) -> 399576.29 | E6: =(D6-C6)/C6 -> 0.1643861
B7: Terraced | C7: =AVERAGE(Copy!C4:C521) -> 341067.57 | D7: =AVERAGE(Copy!C14:C799) -> 402478.37 | E7: =(D7-C7)/C7 -> 0.18005466
B10: East Midlands East of England London North East North West South East South West West Midlands Yorkshire
C11: 2023 | D11: 2024
B12: East Midlands | C12: =AVERAGE(Copy!C6:C511) -> 339418.97
B13: East of England | C13: =AVERAGE(Copy!C10:C533) -> 344095.42
B14: London | C14: =AVERAGE(Copy!C2:C525) -> 341188.93
B15: North East | C15: =AVERAGE(Copy!C18:C532) -> 346363.11
B16: North West
B17: South East
B18: South West
B19: West Midlands
B20: Yorkshire
